{"domain": "apache.org", "pageload_start_ts": 1685749622.7332177, "pageload_end_ts": 1685749627.3056011, "post_pageload_url": "https://www.apache.org/", "errors": {"page_load_timeout": 0, "dns": 0, "consent_click": 0}, "tracker_domains": ["google.com"], "tracker_entities": ["http://www.google.com/"], "request_headers": [[["Host", "www.apache.org"], ["Proxy-Connection", "keep-alive"], ["Upgrade-Insecure-Requests", "1"], ["User-Agent", "Mozilla/5.0 (X11; Linux x86_64) AppleWebKit/537.36 (KHTML, like Gecko) HeadlessChrome/114.0.5735.90 Safari/537.36"], ["Accept", "text/html,application/xhtml+xml,application/xml;q=0.9,image/avif,image/webp,image/apng,*/*;q=0.8,application/signed-exchange;v=b3;q=0.7"], ["Accept-Encoding", "gzip, deflate"]], [["upgrade-insecure-requests", "1"], ["user-agent", "Mozilla/5.0 (X11; Linux x86_64) AppleWebKit/537.36 (KHTML, like Gecko) HeadlessChrome/114.0.5735.90 Safari/537.36"], ["accept", "text/html,application/xhtml+xml,application/xml;q=0.9,image/avif,image/webp,image/apng,*/*;q=0.8,application/signed-exchange;v=b3;q=0.7"], ["sec-fetch-site", "none"], ["sec-fetch-mode", "navigate"], ["sec-fetch-user", "?1"], ["sec-fetch-dest", "document"], ["sec-ch-ua", "\"Not.A/Brand\";v=\"8\", \"Chromium\";v=\"114\", \"HeadlessChrome\";v=\"114\""], ["sec-ch-ua-mobile", "?0"], ["sec-ch-ua-platform", "\"Linux\""], ["accept-encoding", "gzip, deflate, br"]], [["sec-ch-ua", "\"Not.A/Brand\";v=\"8\", \"Chromium\";v=\"114\", \"HeadlessChrome\";v=\"114\""], ["sec-ch-ua-mobile", "?0"], ["user-agent", "Mozilla/5.0 (X11; Linux x86_64) AppleWebKit/537.36 (KHTML, like Gecko) HeadlessChrome/114.0.5735.90 Safari/537.36"], ["sec-ch-ua-platform", "\"Linux\""], ["accept", "text/css,*/*;q=0.1"], ["sec-fetch-site", "same-origin"], ["sec-fetch-mode", "no-cors"], ["sec-fetch-dest", "style"], ["referer", "https://www.apache.org/"], ["accept-encoding", "gzip, deflate, br"]], [["sec-ch-ua", "\"Not.A/Brand\";v=\"8\", \"Chromium\";v=\"114\", \"HeadlessChrome\";v=\"114\""], ["sec-ch-ua-mobile", "?0"], ["user-agent", "Mozilla/5.0 (X11; Linux x86_64) AppleWebKit/537.36 (KHTML, like Gecko) HeadlessChrome/114.0.5735.90 Safari/537.36"], ["sec-ch-ua-platform", "\"Linux\""], ["accept", "text/css,*/*;q=0.1"], ["sec-fetch-site", "same-origin"], ["sec-fetch-mode", "no-cors"], ["sec-fetch-dest", "style"], ["referer", "https://www.apache.org/"], ["accept-encoding", "gzip, deflate, br"]], [["sec-ch-ua", "\"Not.A/Brand\";v=\"8\", \"Chromium\";v=\"114\", \"HeadlessChrome\";v=\"114\""], ["sec-ch-ua-mobile", "?0"], ["user-agent", "Mozilla/5.0 (X11; Linux x86_64) AppleWebKit/537.36 (KHTML, like Gecko) HeadlessChrome/114.0.5735.90 Safari/537.36"], ["sec-ch-ua-platform", "\"Linux\""], ["accept", "text/css,*/*;q=0.1"], ["sec-fetch-site", "same-origin"], ["sec-fetch-mode", "no-cors"], ["sec-fetch-dest", "style"], ["referer", "https://www.apache.org/"], ["accept-encoding", "gzip, deflate, br"]], [["sec-ch-ua", "\"Not.A/Brand\";v=\"8\", \"Chromium\";v=\"114\", \"HeadlessChrome\";v=\"114\""], ["sec-ch-ua-mobile", "?0"], ["user-agent", "Mozilla/5.0 (X11; Linux x86_64) AppleWebKit/537.36 (KHTML, like Gecko) HeadlessChrome/114.0.5735.90 Safari/537.36"], ["sec-ch-ua-platform", "\"Linux\""], ["accept", "*/*"], ["sec-fetch-site", "same-origin"], ["sec-fetch-mode", "no-cors"], ["sec-fetch-dest", "script"], ["referer", "https://www.apache.org/"], ["accept-encoding", "gzip, deflate, br"]], [["sec-ch-ua", "\"Not.A/Brand\";v=\"8\", \"Chromium\";v=\"114\", \"HeadlessChrome\";v=\"114\""], ["sec-ch-ua-mobile", "?0"], ["user-agent", "Mozilla/5.0 (X11; Linux x86_64) AppleWebKit/537.36 (KHTML, like Gecko) HeadlessChrome/114.0.5735.90 Safari/537.36"], ["sec-ch-ua-platform", "\"Linux\""], ["accept", "*/*"], ["sec-fetch-site", "same-origin"], ["sec-fetch-mode", "no-cors"], ["sec-fetch-dest", "script"], ["referer", "https://www.apache.org/"], ["accept-encoding", "gzip, deflate, br"]], [["sec-ch-ua", "\"Not.A/Brand\";v=\"8\", \"Chromium\";v=\"114\", \"HeadlessChrome\";v=\"114\""], ["sec-ch-ua-mobile", "?0"], ["user-agent", "Mozilla/5.0 (X11; Linux x86_64) AppleWebKit/537.36 (KHTML, like Gecko) HeadlessChrome/114.0.5735.90 Safari/537.36"], ["sec-ch-ua-platform", "\"Linux\""], ["accept", "*/*"], ["sec-fetch-site", "same-origin"], ["sec-fetch-mode", "no-cors"], ["sec-fetch-dest", "script"], ["referer", "https://www.apache.org/"], ["accept-encoding", "gzip, deflate, br"]], [["sec-ch-ua", "\"Not.A/Brand\";v=\"8\", \"Chromium\";v=\"114\", \"HeadlessChrome\";v=\"114\""], ["sec-ch-ua-mobile", "?0"], ["user-agent", "Mozilla/5.0 (X11; Linux x86_64) AppleWebKit/537.36 (KHTML, like Gecko) HeadlessChrome/114.0.5735.90 Safari/537.36"], ["sec-ch-ua-platform", "\"Linux\""], ["accept", "image/avif,image/webp,image/apng,image/svg+xml,image/*,*/*;q=0.8"], ["sec-fetch-site", "same-origin"], ["sec-fetch-mode", "no-cors"], ["sec-fetch-dest", "image"], ["referer", "https://www.apache.org/"], ["accept-encoding", "gzip, deflate, br"]], [["sec-ch-ua", "\"Not.A/Brand\";v=\"8\", \"Chromium\";v=\"114\", \"HeadlessChrome\";v=\"114\""], ["sec-ch-ua-mobile", "?0"], ["user-agent", "Mozilla/5.0 (X11; Linux x86_64) AppleWebKit/537.36 (KHTML, like Gecko) HeadlessChrome/114.0.5735.90 Safari/537.36"], ["sec-ch-ua-platform", "\"Linux\""], ["accept", "image/avif,image/webp,image/apng,image/svg+xml,image/*,*/*;q=0.8"], ["sec-fetch-site", "same-origin"], ["sec-fetch-mode", "no-cors"], ["sec-fetch-dest", "image"], ["referer", "https://www.apache.org/"], ["accept-encoding", "gzip, deflate, br"]], [["sec-ch-ua", "\"Not.A/Brand\";v=\"8\", \"Chromium\";v=\"114\", \"HeadlessChrome\";v=\"114\""], ["sec-ch-ua-mobile", "?0"], ["user-agent", "Mozilla/5.0 (X11; Linux x86_64) AppleWebKit/537.36 (KHTML, like Gecko) HeadlessChrome/114.0.5735.90 Safari/537.36"], ["sec-ch-ua-platform", "\"Linux\""], ["accept", "image/avif,image/webp,image/apng,image/svg+xml,image/*,*/*;q=0.8"], ["sec-fetch-site", "same-origin"], ["sec-fetch-mode", "no-cors"], ["sec-fetch-dest", "image"], ["referer", "https://www.apache.org/"], ["accept-encoding", "gzip, deflate, br"]], [["sec-ch-ua", "\"Not.A/Brand\";v=\"8\", \"Chromium\";v=\"114\", \"HeadlessChrome\";v=\"114\""], ["sec-ch-ua-mobile", "?0"], ["user-agent", "Mozilla/5.0 (X11; Linux x86_64) AppleWebKit/537.36 (KHTML, like Gecko) HeadlessChrome/114.0.5735.90 Safari/537.36"], ["sec-ch-ua-platform", "\"Linux\""], ["accept", "image/avif,image/webp,image/apng,image/svg+xml,image/*,*/*;q=0.8"], ["sec-fetch-site", "same-origin"], ["sec-fetch-mode", "no-cors"], ["sec-fetch-dest", "image"], ["referer", "https://www.apache.org/"], ["accept-encoding", "gzip, deflate, br"]], [["sec-ch-ua", "\"Not.A/Brand\";v=\"8\", \"Chromium\";v=\"114\", \"HeadlessChrome\";v=\"114\""], ["sec-ch-ua-mobile", "?0"], ["user-agent", "Mozilla/5.0 (X11; Linux x86_64) AppleWebKit/537.36 (KHTML, like Gecko) HeadlessChrome/114.0.5735.90 Safari/537.36"], ["sec-ch-ua-platform", "\"Linux\""], ["accept", "image/avif,image/webp,image/apng,image/svg+xml,image/*,*/*;q=0.8"], ["sec-fetch-site", "same-origin"], ["sec-fetch-mode", "no-cors"], ["sec-fetch-dest", "image"], ["referer", "https://www.apache.org/"], ["accept-encoding", "gzip, deflate, br"]], [["sec-ch-ua", "\"Not.A/Brand\";v=\"8\", \"Chromium\";v=\"114\", \"HeadlessChrome\";v=\"114\""], ["sec-ch-ua-mobile", "?0"], ["user-agent", "Mozilla/5.0 (X11; Linux x86_64) AppleWebKit/537.36 (KHTML, like Gecko) HeadlessChrome/114.0.5735.90 Safari/537.36"], ["sec-ch-ua-platform", "\"Linux\""], ["accept", "image/avif,image/webp,image/apng,image/svg+xml,image/*,*/*;q=0.8"], ["sec-fetch-site", "same-origin"], ["sec-fetch-mode", "no-cors"], ["sec-fetch-dest", "image"], ["referer", "https://www.apache.org/"], ["accept-encoding", "gzip, deflate, br"]], [["sec-ch-ua", "\"Not.A/Brand\";v=\"8\", \"Chromium\";v=\"114\", \"HeadlessChrome\";v=\"114\""], ["sec-ch-ua-mobile", "?0"], ["user-agent", "Mozilla/5.0 (X11; Linux x86_64) AppleWebKit/537.36 (KHTML, like Gecko) HeadlessChrome/114.0.5735.90 Safari/537.36"], ["sec-ch-ua-platform", "\"Linux\""], ["accept", "image/avif,image/webp,image/apng,image/svg+xml,image/*,*/*;q=0.8"], ["sec-fetch-site", "same-origin"], ["sec-fetch-mode", "no-cors"], ["sec-fetch-dest", "image"], ["referer", "https://www.apache.org/"], ["accept-encoding", "gzip, deflate, br"]], [["sec-ch-ua", "\"Not.A/Brand\";v=\"8\", \"Chromium\";v=\"114\", \"HeadlessChrome\";v=\"114\""], ["sec-ch-ua-mobile", "?0"], ["user-agent", "Mozilla/5.0 (X11; Linux x86_64) AppleWebKit/537.36 (KHTML, like Gecko) HeadlessChrome/114.0.5735.90 Safari/537.36"], ["sec-ch-ua-platform", "\"Linux\""], ["accept", "image/avif,image/webp,image/apng,image/svg+xml,image/*,*/*;q=0.8"], ["sec-fetch-site", "same-origin"], ["sec-fetch-mode", "no-cors"], ["sec-fetch-dest", "image"], ["referer", "https://www.apache.org/"], ["accept-encoding", "gzip, deflate, br"]], [["sec-ch-ua", "\"Not.A/Brand\";v=\"8\", \"Chromium\";v=\"114\", \"HeadlessChrome\";v=\"114\""], ["sec-ch-ua-mobile", "?0"], ["user-agent", "Mozilla/5.0 (X11; Linux x86_64) AppleWebKit/537.36 (KHTML, like Gecko) HeadlessChrome/114.0.5735.90 Safari/537.36"], ["sec-ch-ua-platform", "\"Linux\""], ["accept", "image/avif,image/webp,image/apng,image/svg+xml,image/*,*/*;q=0.8"], ["sec-fetch-site", "same-origin"], ["sec-fetch-mode", "no-cors"], ["sec-fetch-dest", "image"], ["referer", "https://www.apache.org/"], ["accept-encoding", "gzip, deflate, br"]], [["sec-ch-ua", "\"Not.A/Brand\";v=\"8\", \"Chromium\";v=\"114\", \"HeadlessChrome\";v=\"114\""], ["sec-ch-ua-mobile", "?0"], ["user-agent", "Mozilla/5.0 (X11; Linux x86_64) AppleWebKit/537.36 (KHTML, like Gecko) HeadlessChrome/114.0.5735.90 Safari/537.36"], ["sec-ch-ua-platform", "\"Linux\""], ["accept", "image/avif,image/webp,image/apng,image/svg+xml,image/*,*/*;q=0.8"], ["sec-fetch-site", "same-origin"], ["sec-fetch-mode", "no-cors"], ["sec-fetch-dest", "image"], ["referer", "https://www.apache.org/"], ["accept-encoding", "gzip, deflate, br"]], [["sec-ch-ua", "\"Not.A/Brand\";v=\"8\", \"Chromium\";v=\"114\", \"HeadlessChrome\";v=\"114\""], ["sec-ch-ua-mobile", "?0"], ["user-agent", "Mozilla/5.0 (X11; Linux x86_64) AppleWebKit/537.36 (KHTML, like Gecko) HeadlessChrome/114.0.5735.90 Safari/537.36"], ["sec-ch-ua-platform", "\"Linux\""], ["accept", "image/avif,image/webp,image/apng,image/svg+xml,image/*,*/*;q=0.8"], ["sec-fetch-site", "same-origin"], ["sec-fetch-mode", "no-cors"], ["sec-fetch-dest", "image"], ["referer", "https://www.apache.org/"], ["accept-encoding", "gzip, deflate, br"]], [["sec-ch-ua", "\"Not.A/Brand\";v=\"8\", \"Chromium\";v=\"114\", \"HeadlessChrome\";v=\"114\""], ["sec-ch-ua-mobile", "?0"], ["user-agent", "Mozilla/5.0 (X11; Linux x86_64) AppleWebKit/537.36 (KHTML, like Gecko) HeadlessChrome/114.0.5735.90 Safari/537.36"], ["sec-ch-ua-platform", "\"Linux\""], ["accept", "image/avif,image/webp,image/apng,image/svg+xml,image/*,*/*;q=0.8"], ["sec-fetch-site", "same-origin"], ["sec-fetch-mode", "no-cors"], ["sec-fetch-dest", "image"], ["referer", "https://www.apache.org/"], ["accept-encoding", "gzip, deflate, br"]], [["sec-ch-ua", "\"Not.A/Brand\";v=\"8\", \"Chromium\";v=\"114\", \"HeadlessChrome\";v=\"114\""], ["sec-ch-ua-mobile", "?0"], ["user-agent", "Mozilla/5.0 (X11; Linux x86_64) AppleWebKit/537.36 (KHTML, like Gecko) HeadlessChrome/114.0.5735.90 Safari/537.36"], ["sec-ch-ua-platform", "\"Linux\""], ["accept", "image/avif,image/webp,image/apng,image/svg+xml,image/*,*/*;q=0.8"], ["sec-fetch-site", "same-origin"], ["sec-fetch-mode", "no-cors"], ["sec-fetch-dest", "image"], ["referer", "https://www.apache.org/"], ["accept-encoding", "gzip, deflate, br"]], [["sec-ch-ua", "\"Not.A/Brand\";v=\"8\", \"Chromium\";v=\"114\", \"HeadlessChrome\";v=\"114\""], ["sec-ch-ua-mobile", "?0"], ["user-agent", "Mozilla/5.0 (X11; Linux x86_64) AppleWebKit/537.36 (KHTML, like Gecko) HeadlessChrome/114.0.5735.90 Safari/537.36"], ["sec-ch-ua-platform", "\"Linux\""], ["accept", "*/*"], ["sec-fetch-site", "cross-site"], ["sec-fetch-mode", "no-cors"], ["sec-fetch-dest", "script"], ["referer", "https://www.apache.org/"], ["accept-encoding", "gzip, deflate, br"]], [["sec-ch-ua", "\"Not.A/Brand\";v=\"8\", \"Chromium\";v=\"114\", \"HeadlessChrome\";v=\"114\""], ["origin", "https://www.apache.org"], ["sec-ch-ua-mobile", "?0"], ["user-agent", "Mozilla/5.0 (X11; Linux x86_64) AppleWebKit/537.36 (KHTML, like Gecko) HeadlessChrome/114.0.5735.90 Safari/537.36"], ["sec-ch-ua-platform", "\"Linux\""], ["accept", "*/*"], ["sec-fetch-site", "same-origin"], ["sec-fetch-mode", "cors"], ["sec-fetch-dest", "font"], ["referer", "https://www.apache.org/css/Montserrat-300-600.css"], ["accept-encoding", "gzip, deflate, br"]], [["sec-ch-ua", "\"Not.A/Brand\";v=\"8\", \"Chromium\";v=\"114\", \"HeadlessChrome\";v=\"114\""], ["origin", "https://www.apache.org"], ["sec-ch-ua-mobile", "?0"], ["user-agent", "Mozilla/5.0 (X11; Linux x86_64) AppleWebKit/537.36 (KHTML, like Gecko) HeadlessChrome/114.0.5735.90 Safari/537.36"], ["sec-ch-ua-platform", "\"Linux\""], ["accept", "*/*"], ["sec-fetch-site", "same-origin"], ["sec-fetch-mode", "cors"], ["sec-fetch-dest", "font"], ["referer", "https://www.apache.org/css/min.bootstrap.css"], ["accept-encoding", "gzip, deflate, br"]], [["sec-ch-ua", "\"Not.A/Brand\";v=\"8\", \"Chromium\";v=\"114\", \"HeadlessChrome\";v=\"114\""], ["origin", "https://www.apache.org"], ["sec-ch-ua-mobile", "?0"], ["user-agent", "Mozilla/5.0 (X11; Linux x86_64) AppleWebKit/537.36 (KHTML, like Gecko) HeadlessChrome/114.0.5735.90 Safari/537.36"], ["sec-ch-ua-platform", "\"Linux\""], ["accept", "*/*"], ["sec-fetch-site", "same-origin"], ["sec-fetch-mode", "cors"], ["sec-fetch-dest", "font"], ["referer", "https://www.apache.org/css/Montserrat-300-600.css"], ["accept-encoding", "gzip, deflate, br"]], [["sec-ch-ua", "\"Not.A/Brand\";v=\"8\", \"Chromium\";v=\"114\", \"HeadlessChrome\";v=\"114\""], ["sec-ch-ua-mobile", "?0"], ["user-agent", "Mozilla/5.0 (X11; Linux x86_64) AppleWebKit/537.36 (KHTML, like Gecko) HeadlessChrome/114.0.5735.90 Safari/537.36"], ["sec-ch-ua-platform", "\"Linux\""], ["accept", "text/css,*/*;q=0.1"], ["sec-fetch-site", "cross-site"], ["sec-fetch-mode", "no-cors"], ["sec-fetch-dest", "style"], ["referer", "https://www.apache.org/"], ["accept-encoding", "gzip, deflate, br"]], [["sec-ch-ua", "\"Not.A/Brand\";v=\"8\", \"Chromium\";v=\"114\", \"HeadlessChrome\";v=\"114\""], ["sec-ch-ua-mobile", "?0"], ["user-agent", "Mozilla/5.0 (X11; Linux x86_64) AppleWebKit/537.36 (KHTML, like Gecko) HeadlessChrome/114.0.5735.90 Safari/537.36"], ["sec-ch-ua-platform", "\"Linux\""], ["accept", "*/*"], ["sec-fetch-site", "cross-site"], ["sec-fetch-mode", "no-cors"], ["sec-fetch-dest", "script"], ["referer", "https://www.apache.org/"], ["accept-encoding", "gzip, deflate, br"]], [["sec-ch-ua", "\"Not.A/Brand\";v=\"8\", \"Chromium\";v=\"114\", \"HeadlessChrome\";v=\"114\""], ["sec-ch-ua-mobile", "?0"], ["user-agent", "Mozilla/5.0 (X11; Linux x86_64) AppleWebKit/537.36 (KHTML, like Gecko) HeadlessChrome/114.0.5735.90 Safari/537.36"], ["sec-ch-ua-platform", "\"Linux\""], ["accept", "text/css,*/*;q=0.1"], ["sec-fetch-site", "cross-site"], ["sec-fetch-mode", "no-cors"], ["sec-fetch-dest", "style"], ["referer", "https://www.apache.org/"], ["accept-encoding", "gzip, deflate, br"]], [["sec-ch-ua", "\"Not.A/Brand\";v=\"8\", \"Chromium\";v=\"114\", \"HeadlessChrome\";v=\"114\""], ["sec-ch-ua-mobile", "?0"], ["user-agent", "Mozilla/5.0 (X11; Linux x86_64) AppleWebKit/537.36 (KHTML, like Gecko) HeadlessChrome/114.0.5735.90 Safari/537.36"], ["sec-ch-ua-platform", "\"Linux\""], ["accept", "*/*"], ["sec-fetch-site", "cross-site"], ["sec-fetch-mode", "no-cors"], ["sec-fetch-dest", "script"], ["referer", "https://www.apache.org/"], ["accept-encoding", "gzip, deflate, br"]], [["sec-ch-ua", "\"Not.A/Brand\";v=\"8\", \"Chromium\";v=\"114\", \"HeadlessChrome\";v=\"114\""], ["sec-ch-ua-mobile", "?0"], ["user-agent", "Mozilla/5.0 (X11; Linux x86_64) AppleWebKit/537.36 (KHTML, like Gecko) HeadlessChrome/114.0.5735.90 Safari/537.36"], ["sec-ch-ua-platform", "\"Linux\""], ["accept", "image/avif,image/webp,image/apng,image/svg+xml,image/*,*/*;q=0.8"], ["sec-fetch-site", "cross-site"], ["sec-fetch-mode", "no-cors"], ["sec-fetch-dest", "image"], ["referer", "https://www.apache.org/"], ["accept-encoding", "gzip, deflate, br"]], [["sec-ch-ua", "\"Not.A/Brand\";v=\"8\", \"Chromium\";v=\"114\", \"HeadlessChrome\";v=\"114\""], ["sec-ch-ua-mobile", "?0"], ["user-agent", "Mozilla/5.0 (X11; Linux x86_64) AppleWebKit/537.36 (KHTML, like Gecko) HeadlessChrome/114.0.5735.90 Safari/537.36"], ["sec-ch-ua-platform", "\"Linux\""], ["accept", "image/avif,image/webp,image/apng,image/svg+xml,image/*,*/*;q=0.8"], ["sec-fetch-site", "cross-site"], ["sec-fetch-mode", "no-cors"], ["sec-fetch-dest", "image"], ["referer", "https://www.apache.org/"], ["accept-encoding", "gzip, deflate, br"]]], "response_headers": [[["Connection", "close"], ["Content-Length", "0"], ["Server", "Varnish"], ["Retry-After", "0"], ["Location", "https://www.apache.org/"], ["Accept-Ranges", "bytes"], ["Date", "Fri, 02 Jun 2023 23:47:02 GMT"], ["Via", "1.1 varnish"], ["X-Served-By", "cache-fra-etou8220033-FRA"], ["X-Cache", "HIT"], ["X-Cache-Hits", "0"], ["X-Timer", "S1685749623.830842,VS0,VE0"]], [["server", "Apache"], ["last-modified", "Fri, 02 Jun 2023 23:23:11 GMT"], ["etag", "\"11a49-5fd2dd6259f10-gzip\""], ["cache-control", "max-age=3600"], ["expires", "Sat, 03 Jun 2023 00:23:12 GMT"], ["content-encoding", "gzip"], ["content-security-policy", "default-src 'self' 'unsafe-inline' https://www.apachecon.com/ https://www.google.com/cse/ https://cse.google.com/ https://www.googleapis.com/generate_204 http://*.google.com/generate_204 https://afs.googlesyndication.com/ https://csp.withgoogle.com/ https://www.google.com/images/ https://ssl.gstatic.com/ui/ https://docs.google.com/forms/ https://www.youtube.com/embed/; script-src 'self' 'unsafe-inline' 'unsafe-eval' https://cse.google.com/ http://cse.google.com/adsense/search/async-ads.js https://www.google"], ["strict-transport-security", "max-age=31536000; preload"], ["content-type", "text/html"], ["via", "1.1 varnish, 1.1 varnish"], ["accept-ranges", "bytes"], ["date", "Fri, 02 Jun 2023 23:47:03 GMT"], ["age", "1431"], ["x-served-by", "cache-hel1410028-HEL, cache-fra-etou8220042-FRA"], ["x-cache", "HIT, HIT"], ["x-cache-hits", "3, 1"], ["x-timer", "S1685749623.163850,VS0,VE1"], ["vary", "Accept-Encoding"], ["content-length", "16096"]], [["server", "Apache"], ["last-modified", "Tue, 03 Jan 2023 14:18:22 GMT"], ["etag", "\"156-5f15cbd87b27d-gzip\""], ["cache-control", "max-age=3600"], ["expires", "Tue, 23 May 2023 09:23:18 GMT"], ["content-encoding", "gzip"], ["content-security-policy", "default-src 'self' 'unsafe-inline' https://www.apachecon.com/ https://www.google.com/cse/ https://cse.google.com/ https://www.googleapis.com/generate_204 http://*.google.com/generate_204 https://afs.googlesyndication.com/ https://csp.withgoogle.com/ https://www.google.com/images/ https://ssl.gstatic.com/ui/ https://docs.google.com/forms/ https://www.youtube.com/embed/; script-src 'self' 'unsafe-inline' 'unsafe-eval' https://cse.google.com/ http://cse.google.com/adsense/search/async-ads.js https://www.google"], ["strict-transport-security", "max-age=31536000; preload"], ["content-type", "text/css"], ["via", "1.1 varnish, 1.1 varnish"], ["accept-ranges", "bytes"], ["date", "Fri, 02 Jun 2023 23:47:03 GMT"], ["age", "1422"], ["x-served-by", "cache-hel1410028-HEL, cache-fra-etou8220042-FRA"], ["x-cache", "MISS, HIT"], ["x-cache-hits", "0, 1"], ["x-timer", "S1685749623.354885,VS0,VE1"], ["vary", "Accept-Encoding"], ["content-length", "181"]], [["server", "Apache"], ["last-modified", "Mon, 16 May 2022 19:23:08 GMT"], ["etag", "\"1c550-5df25f43f6132-gzip\""], ["cache-control", "max-age=3600"], ["expires", "Thu, 01 Jun 2023 09:23:18 GMT"], ["content-encoding", "gzip"], ["content-security-policy", "default-src 'self' 'unsafe-inline' https://www.apachecon.com/ https://www.google.com/cse/ https://cse.google.com/ https://www.googleapis.com/generate_204 http://*.google.com/generate_204 https://afs.googlesyndication.com/ https://csp.withgoogle.com/ https://www.google.com/images/ https://ssl.gstatic.com/ui/ https://docs.google.com/forms/ https://www.youtube.com/embed/; script-src 'self' 'unsafe-inline' 'unsafe-eval' https://cse.google.com/ http://cse.google.com/adsense/search/async-ads.js https://www.google"], ["strict-transport-security", "max-age=31536000; preload"], ["content-type", "text/css"], ["via", "1.1 varnish, 1.1 varnish"], ["accept-ranges", "bytes"], ["date", "Fri, 02 Jun 2023 23:47:03 GMT"], ["age", "1422"], ["x-served-by", "cache-hel1410020-HEL, cache-fra-etou8220042-FRA"], ["x-cache", "HIT, HIT"], ["x-cache-hits", "7, 1"], ["x-timer", "S1685749623.395576,VS0,VE1"], ["vary", "Accept-Encoding"], ["content-length", "19216"]], [["server", "Apache"], ["last-modified", "Thu, 23 Feb 2023 21:52:49 GMT"], ["etag", "\"2206-5f56508a57ef7-gzip\""], ["cache-control", "max-age=3600"], ["expires", "Thu, 01 Jun 2023 09:23:18 GMT"], ["content-encoding", "gzip"], ["content-security-policy", "default-src 'self' 'unsafe-inline' https://www.apachecon.com/ https://www.google.com/cse/ https://cse.google.com/ https://www.googleapis.com/generate_204 http://*.google.com/generate_204 https://afs.googlesyndication.com/ https://csp.withgoogle.com/ https://www.google.com/images/ https://ssl.gstatic.com/ui/ https://docs.google.com/forms/ https://www.youtube.com/embed/; script-src 'self' 'unsafe-inline' 'unsafe-eval' https://cse.google.com/ http://cse.google.com/adsense/search/async-ads.js https://www.google"], ["strict-transport-security", "max-age=31536000; preload"], ["content-type", "text/css"], ["via", "1.1 varnish, 1.1 varnish"], ["accept-ranges", "bytes"], ["date", "Fri, 02 Jun 2023 23:47:03 GMT"], ["age", "1422"], ["x-served-by", "cache-hel1410024-HEL, cache-fra-etou8220042-FRA"], ["x-cache", "HIT, HIT"], ["x-cache-hits", "2, 1"], ["x-timer", "S1685749623.387107,VS0,VE1"], ["vary", "Accept-Encoding"], ["content-length", "2472"]], [["server", "Apache"], ["last-modified", "Sat, 08 Apr 2023 22:42:18 GMT"], ["etag", "\"15ec3-5f8dadaa25f28-gzip\""], ["cache-control", "max-age=3600"], ["expires", "Tue, 23 May 2023 09:23:18 GMT"], ["content-encoding", "gzip"], ["content-security-policy", "default-src 'self' 'unsafe-inline' https://www.apachecon.com/ https://www.google.com/cse/ https://cse.google.com/ https://www.googleapis.com/generate_204 http://*.google.com/generate_204 https://afs.googlesyndication.com/ https://csp.withgoogle.com/ https://www.google.com/images/ https://ssl.gstatic.com/ui/ https://docs.google.com/forms/ https://www.youtube.com/embed/; script-src 'self' 'unsafe-inline' 'unsafe-eval' https://cse.google.com/ http://cse.google.com/adsense/search/async-ads.js https://www.google"], ["strict-transport-security", "max-age=31536000; preload"], ["content-type", "application/javascript"], ["via", "1.1 varnish, 1.1 varnish"], ["accept-ranges", "bytes"], ["date", "Fri, 02 Jun 2023 23:47:03 GMT"], ["age", "1421"], ["x-served-by", "cache-hel1410022-HEL, cache-fra-etou8220042-FRA"], ["x-cache", "MISS, HIT"], ["x-cache-hits", "0, 1"], ["x-timer", "S1685749623.408086,VS0,VE1"], ["vary", "Accept-Encoding"], ["content-length", "31043"]], [["server", "Apache"], ["last-modified", "Wed, 04 Jan 2023 00:23:23 GMT"], ["etag", "\"2f4-5f16531422cfd-gzip\""], ["cache-control", "max-age=3600"], ["expires", "Tue, 23 May 2023 05:23:18 GMT"], ["content-encoding", "gzip"], ["content-security-policy", "default-src 'self' 'unsafe-inline' https://www.apachecon.com/ https://www.google.com/cse/ https://cse.google.com/ https://www.googleapis.com/generate_204 http://*.google.com/generate_204 https://afs.googlesyndication.com/ https://csp.withgoogle.com/ https://www.google.com/images/ https://ssl.gstatic.com/ui/ https://docs.google.com/forms/ https://www.youtube.com/embed/; script-src 'self' 'unsafe-inline' 'unsafe-eval' https://cse.google.com/ http://cse.google.com/adsense/search/async-ads.js https://www.google"], ["strict-transport-security", "max-age=31536000; preload"], ["content-type", "application/javascript"], ["via", "1.1 varnish, 1.1 varnish"], ["accept-ranges", "bytes"], ["date", "Fri, 02 Jun 2023 23:47:03 GMT"], ["age", "1422"], ["x-served-by", "cache-hel1410033-HEL, cache-fra-etou8220042-FRA"], ["x-cache", "HIT, HIT"], ["x-cache-hits", "4, 1"], ["x-timer", "S1685749623.416281,VS0,VE1"], ["vary", "Accept-Encoding"], ["content-length", "333"]], [["server", "Apache"], ["last-modified", "Mon, 16 May 2022 19:23:11 GMT"], ["etag", "\"df79-5df25f4712f3a-gzip\""], ["cache-control", "max-age=3600"], ["expires", "Fri, 26 May 2023 13:23:17 GMT"], ["content-encoding", "gzip"], ["content-security-policy", "default-src 'self' 'unsafe-inline' https://www.apachecon.com/ https://www.google.com/cse/ https://cse.google.com/ https://www.googleapis.com/generate_204 http://*.google.com/generate_204 https://afs.googlesyndication.com/ https://csp.withgoogle.com/ https://www.google.com/images/ https://ssl.gstatic.com/ui/ https://docs.google.com/forms/ https://www.youtube.com/embed/; script-src 'self' 'unsafe-inline' 'unsafe-eval' https://cse.google.com/ http://cse.google.com/adsense/search/async-ads.js https://www.google"], ["strict-transport-security", "max-age=31536000; preload"], ["content-type", "application/javascript"], ["via", "1.1 varnish, 1.1 varnish"], ["accept-ranges", "bytes"], ["date", "Fri, 02 Jun 2023 23:47:03 GMT"], ["age", "1422"], ["x-served-by", "cache-hel1410029-HEL, cache-fra-etou8220042-FRA"], ["x-cache", "HIT, HIT"], ["x-cache-hits", "2, 1"], ["x-timer", "S1685749623.425619,VS0,VE1"], ["vary", "Accept-Encoding"], ["content-length", "11183"]], [["server", "Apache"], ["last-modified", "Tue, 17 Jan 2023 17:40:06 GMT"], ["etag", "\"24b9-5f27930bfd40c\""], ["cache-control", "max-age=3600"], ["expires", "Tue, 30 May 2023 04:23:16 GMT"], ["content-security-policy", "default-src 'self' 'unsafe-inline' https://www.apachecon.com/ https://www.google.com/cse/ https://cse.google.com/ https://www.googleapis.com/generate_204 http://*.google.com/generate_204 https://afs.googlesyndication.com/ https://csp.withgoogle.com/ https://www.google.com/images/ https://ssl.gstatic.com/ui/ https://docs.google.com/forms/ https://www.youtube.com/embed/; script-src 'self' 'unsafe-inline' 'unsafe-eval' https://cse.google.com/ http://cse.google.com/adsense/search/async-ads.js https://www.google"], ["strict-transport-security", "max-age=31536000; preload"], ["content-type", "image/png"], ["via", "1.1 varnish, 1.1 varnish"], ["accept-ranges", "bytes"], ["date", "Fri, 02 Jun 2023 23:47:03 GMT"], ["age", "1422"], ["x-served-by", "cache-hel1410020-HEL, cache-fra-etou8220042-FRA"], ["x-cache", "HIT, HIT"], ["x-cache-hits", "2, 1"], ["x-timer", "S1685749623.434241,VS0,VE1"], ["content-length", "9401"]], [["server", "Apache"], ["last-modified", "Thu, 23 Feb 2023 21:52:49 GMT"], ["etag", "\"70a04-5f56508a5cd17\""], ["cache-control", "max-age=3600"], ["expires", "Wed, 31 May 2023 22:11:09 GMT"], ["content-security-policy", "default-src 'self' 'unsafe-inline' https://www.apachecon.com/ https://www.google.com/cse/ https://cse.google.com/ https://www.googleapis.com/generate_204 http://*.google.com/generate_204 https://afs.googlesyndication.com/ https://csp.withgoogle.com/ https://www.google.com/images/ https://ssl.gstatic.com/ui/ https://docs.google.com/forms/ https://www.youtube.com/embed/; script-src 'self' 'unsafe-inline' 'unsafe-eval' https://cse.google.com/ http://cse.google.com/adsense/search/async-ads.js https://www.google"], ["strict-transport-security", "max-age=31536000; preload"], ["content-type", "image/jpeg"], ["via", "1.1 varnish, 1.1 varnish"], ["accept-ranges", "bytes"], ["date", "Fri, 02 Jun 2023 23:47:03 GMT"], ["age", "1418"], ["x-served-by", "cache-hel1410027-HEL, cache-fra-etou8220042-FRA"], ["x-cache", "HIT, HIT"], ["x-cache-hits", "1, 1"], ["x-timer", "S1685749623.442964,VS0,VE1"], ["content-length", "461316"]], [["server", "Apache"], ["last-modified", "Mon, 16 May 2022 19:23:11 GMT"], ["etag", "\"da63-5df25f470f0ba\""], ["cache-control", "max-age=3600"], ["expires", "Tue, 16 May 2023 02:23:19 GMT"], ["content-security-policy", "default-src 'self' 'unsafe-inline' https://www.apachecon.com/ https://www.google.com/cse/ https://cse.google.com/ https://www.googleapis.com/generate_204 http://*.google.com/generate_204 https://afs.googlesyndication.com/ https://csp.withgoogle.com/ https://www.google.com/images/ https://ssl.gstatic.com/ui/ https://docs.google.com/forms/ https://www.youtube.com/embed/; script-src 'self' 'unsafe-inline' 'unsafe-eval' https://cse.google.com/ http://cse.google.com/adsense/search/async-ads.js https://www.google"], ["strict-transport-security", "max-age=31536000; preload"], ["content-type", "image/jpeg"], ["via", "1.1 varnish, 1.1 varnish"], ["accept-ranges", "bytes"], ["date", "Fri, 02 Jun 2023 23:47:03 GMT"], ["age", "1422"], ["x-served-by", "cache-hel1410024-HEL, cache-fra-etou8220042-FRA"], ["x-cache", "HIT, HIT"], ["x-cache-hits", "5, 1"], ["x-timer", "S1685749623.442963,VS0,VE1"], ["content-length", "55907"]], [["server", "Apache"], ["last-modified", "Mon, 16 May 2022 19:23:11 GMT"], ["etag", "\"9414-5df25f470e11a\""], ["cache-control", "max-age=3600"], ["expires", "Tue, 09 May 2023 03:23:23 GMT"], ["content-security-policy", "default-src 'self' 'unsafe-inline' https://www.apachecon.com/ https://www.google.com/cse/ https://cse.google.com/ https://www.googleapis.com/generate_204 http://*.google.com/generate_204 https://afs.googlesyndication.com/ https://csp.withgoogle.com/ https://www.google.com/images/ https://ssl.gstatic.com/ui/ https://docs.google.com/forms/ https://www.youtube.com/embed/; script-src 'self' 'unsafe-inline' 'unsafe-eval' https://cse.google.com/ http://cse.google.com/adsense/search/async-ads.js https://www.google"], ["strict-transport-security", "max-age=31536000; preload"], ["content-type", "image/jpeg"], ["via", "1.1 varnish, 1.1 varnish"], ["accept-ranges", "bytes"], ["date", "Fri, 02 Jun 2023 23:47:03 GMT"], ["age", "1419"], ["x-served-by", "cache-hel1410029-HEL, cache-fra-etou8220042-FRA"], ["x-cache", "HIT, HIT"], ["x-cache-hits", "3, 1"], ["x-timer", "S1685749623.487383,VS0,VE1"], ["content-length", "37908"]], [["server", "Apache"], ["last-modified", "Mon, 16 May 2022 19:23:11 GMT"], ["etag", "\"13d53-5df25f471005a\""], ["cache-control", "max-age=3600"], ["expires", "Tue, 11 Apr 2023 02:27:13 GMT"], ["content-security-policy", "default-src 'self' 'unsafe-inline' https://www.apachecon.com/ https://www.google.com/cse/ https://cse.google.com/ https://www.googleapis.com/generate_204 http://*.google.com/generate_204 https://afs.googlesyndication.com/ https://csp.withgoogle.com/ https://www.google.com/images/ https://ssl.gstatic.com/ui/ https://docs.google.com/forms/ https://www.youtube.com/embed/; script-src 'self' 'unsafe-inline' 'unsafe-eval' https://cse.google.com/ http://cse.google.com/adsense/search/async-ads.js https://www.google"], ["strict-transport-security", "max-age=31536000; preload"], ["content-type", "image/jpeg"], ["via", "1.1 varnish, 1.1 varnish"], ["accept-ranges", "bytes"], ["date", "Fri, 02 Jun 2023 23:47:03 GMT"], ["age", "1419"], ["x-served-by", "cache-hel1410024-HEL, cache-fra-etou8220042-FRA"], ["x-cache", "HIT, HIT"], ["x-cache-hits", "1, 1"], ["x-timer", "S1685749623.494353,VS0,VE1"], ["content-length", "81235"]], [["server", "Apache"], ["last-modified", "Mon, 16 May 2022 19:23:11 GMT"], ["etag", "\"9ed0-5df25f4711f9a\""], ["cache-control", "max-age=3600"], ["expires", "Tue, 09 May 2023 02:23:24 GMT"], ["content-security-policy", "default-src 'self' 'unsafe-inline' https://www.apachecon.com/ https://www.google.com/cse/ https://cse.google.com/ https://www.googleapis.com/generate_204 http://*.google.com/generate_204 https://afs.googlesyndication.com/ https://csp.withgoogle.com/ https://www.google.com/images/ https://ssl.gstatic.com/ui/ https://docs.google.com/forms/ https://www.youtube.com/embed/; script-src 'self' 'unsafe-inline' 'unsafe-eval' https://cse.google.com/ http://cse.google.com/adsense/search/async-ads.js https://www.google"], ["strict-transport-security", "max-age=31536000; preload"], ["content-type", "image/jpeg"], ["via", "1.1 varnish, 1.1 varnish"], ["accept-ranges", "bytes"], ["date", "Fri, 02 Jun 2023 23:47:03 GMT"], ["age", "1418"], ["x-served-by", "cache-hel1410025-HEL, cache-fra-etou8220042-FRA"], ["x-cache", "HIT, HIT"], ["x-cache-hits", "5, 1"], ["x-timer", "S1685749624.503061,VS0,VE1"], ["content-length", "40656"]], [["server", "Apache"], ["last-modified", "Mon, 16 May 2022 19:23:11 GMT"], ["etag", "\"da5b-5df25f470f0ba\""], ["cache-control", "max-age=3600"], ["expires", "Tue, 09 May 2023 02:20:03 GMT"], ["content-security-policy", "default-src 'self' 'unsafe-inline' https://www.apachecon.com/ https://www.google.com/cse/ https://cse.google.com/ https://www.googleapis.com/generate_204 http://*.google.com/generate_204 https://afs.googlesyndication.com/ https://csp.withgoogle.com/ https://www.google.com/images/ https://ssl.gstatic.com/ui/ https://docs.google.com/forms/ https://www.youtube.com/embed/; script-src 'self' 'unsafe-inline' 'unsafe-eval' https://cse.google.com/ http://cse.google.com/adsense/search/async-ads.js https://www.google"], ["strict-transport-security", "max-age=31536000; preload"], ["content-type", "image/jpeg"], ["via", "1.1 varnish, 1.1 varnish"], ["accept-ranges", "bytes"], ["date", "Fri, 02 Jun 2023 23:47:03 GMT"], ["age", "1419"], ["x-served-by", "cache-hel1410034-HEL, cache-fra-etou8220042-FRA"], ["x-cache", "HIT, HIT"], ["x-cache-hits", "4, 1"], ["x-timer", "S1685749624.502997,VS0,VE1"], ["content-length", "55899"]], [["server", "Apache/2.4.29 (Ubuntu)"], ["last-modified", "Mon, 12 Aug 2019 09:08:05 GMT"], ["etag", "\"b724-58fe7dca54a5a\""], ["content-type", "image/png"], ["via", "1.1 www.apache.org, 1.1 varnish, 1.1 varnish"], ["cache-control", "max-age=3600"], ["expires", "Sat, 03 Jun 2023 00:23:25 GMT"], ["content-security-policy", "default-src 'self' 'unsafe-inline' https://www.apachecon.com/ https://www.google.com/cse/ https://cse.google.com/ https://www.googleapis.com/generate_204 http://*.google.com/generate_204 https://afs.googlesyndication.com/ https://csp.withgoogle.com/ https://www.google.com/images/ https://ssl.gstatic.com/ui/ https://docs.google.com/forms/ https://www.youtube.com/embed/; script-src 'self' 'unsafe-inline' 'unsafe-eval' https://cse.google.com/ http://cse.google.com/adsense/search/async-ads.js https://www.google"], ["strict-transport-security", "max-age=31536000; preload"], ["accept-ranges", "bytes"], ["date", "Fri, 02 Jun 2023 23:47:03 GMT"], ["age", "1419"], ["x-served-by", "cache-hel1410029-HEL, cache-fra-etou8220042-FRA"], ["x-cache", "HIT, HIT"], ["x-cache-hits", "1, 1"], ["x-timer", "S1685749624.625672,VS0,VE1"], ["content-length", "46884"]], [["server", "Apache/2.4.29 (Ubuntu)"], ["last-modified", "Mon, 12 Aug 2019 09:19:02 GMT"], ["etag", "\"c86c-58fe803d4273d\""], ["content-type", "image/png"], ["via", "1.1 www.apache.org, 1.1 varnish, 1.1 varnish"], ["cache-control", "max-age=3600"], ["expires", "Fri, 02 Jun 2023 13:07:51 GMT"], ["content-security-policy", "default-src 'self' 'unsafe-inline' https://www.apachecon.com/ https://www.google.com/cse/ https://cse.google.com/ https://www.googleapis.com/generate_204 http://*.google.com/generate_204 https://afs.googlesyndication.com/ https://csp.withgoogle.com/ https://www.google.com/images/ https://ssl.gstatic.com/ui/ https://docs.google.com/forms/ https://www.youtube.com/embed/; script-src 'self' 'unsafe-inline' 'unsafe-eval' https://cse.google.com/ http://cse.google.com/adsense/search/async-ads.js https://www.google"], ["strict-transport-security", "max-age=31536000; preload"], ["accept-ranges", "bytes"], ["date", "Fri, 02 Jun 2023 23:47:03 GMT"], ["age", "1419"], ["x-served-by", "cache-hel1410029-HEL, cache-fra-etou8220042-FRA"], ["x-cache", "HIT, HIT"], ["x-cache-hits", "3, 1"], ["x-timer", "S1685749624.635410,VS0,VE1"], ["content-length", "51308"]], [["server", "Apache/2.4.29 (Ubuntu)"], ["last-modified", "Mon, 12 Aug 2019 09:14:45 GMT"], ["etag", "\"4611-58fe7f47a63ed\""], ["content-type", "image/png"], ["via", "1.1 www.apache.org, 1.1 varnish, 1.1 varnish"], ["cache-control", "max-age=3600"], ["expires", "Fri, 02 Jun 2023 13:07:51 GMT"], ["content-security-policy", "default-src 'self' 'unsafe-inline' https://www.apachecon.com/ https://www.google.com/cse/ https://cse.google.com/ https://www.googleapis.com/generate_204 http://*.google.com/generate_204 https://afs.googlesyndication.com/ https://csp.withgoogle.com/ https://www.google.com/images/ https://ssl.gstatic.com/ui/ https://docs.google.com/forms/ https://www.youtube.com/embed/; script-src 'self' 'unsafe-inline' 'unsafe-eval' https://cse.google.com/ http://cse.google.com/adsense/search/async-ads.js https://www.google"], ["strict-transport-security", "max-age=31536000; preload"], ["accept-ranges", "bytes"], ["date", "Fri, 02 Jun 2023 23:47:03 GMT"], ["age", "1419"], ["x-served-by", "cache-hel1410023-HEL, cache-fra-etou8220042-FRA"], ["x-cache", "HIT, HIT"], ["x-cache-hits", "6, 1"], ["x-timer", "S1685749624.651918,VS0,VE1"], ["content-length", "17937"]], [["server", "Apache/2.4.29 (Ubuntu)"], ["last-modified", "Mon, 12 Aug 2019 09:21:25 GMT"], ["etag", "\"444e-58fe80c4b76e2\""], ["content-type", "image/png"], ["via", "1.1 www.apache.org, 1.1 varnish, 1.1 varnish"], ["cache-control", "max-age=3600"], ["expires", "Thu, 01 Jun 2023 12:13:36 GMT"], ["content-security-policy", "default-src 'self' 'unsafe-inline' https://www.apachecon.com/ https://www.google.com/cse/ https://cse.google.com/ https://www.googleapis.com/generate_204 http://*.google.com/generate_204 https://afs.googlesyndication.com/ https://csp.withgoogle.com/ https://www.google.com/images/ https://ssl.gstatic.com/ui/ https://docs.google.com/forms/ https://www.youtube.com/embed/; script-src 'self' 'unsafe-inline' 'unsafe-eval' https://cse.google.com/ http://cse.google.com/adsense/search/async-ads.js https://www.google"], ["strict-transport-security", "max-age=31536000; preload"], ["accept-ranges", "bytes"], ["date", "Fri, 02 Jun 2023 23:47:03 GMT"], ["age", "1419"], ["x-served-by", "cache-hel1410025-HEL, cache-fra-etou8220042-FRA"], ["x-cache", "MISS, HIT"], ["x-cache-hits", "0, 1"], ["x-timer", "S1685749624.682587,VS0,VE1"], ["content-length", "17486"]], [["server", "Apache/2.4.29 (Ubuntu)"], ["last-modified", "Mon, 12 Aug 2019 09:18:52 GMT"], ["etag", "\"760f-58fe80330d14a\""], ["content-type", "image/png"], ["via", "1.1 www.apache.org, 1.1 varnish, 1.1 varnish"], ["cache-control", "max-age=3600"], ["expires", "Sat, 03 Jun 2023 00:23:25 GMT"], ["content-security-policy", "default-src 'self' 'unsafe-inline' https://www.apachecon.com/ https://www.google.com/cse/ https://cse.google.com/ https://www.googleapis.com/generate_204 http://*.google.com/generate_204 https://afs.googlesyndication.com/ https://csp.withgoogle.com/ https://www.google.com/images/ https://ssl.gstatic.com/ui/ https://docs.google.com/forms/ https://www.youtube.com/embed/; script-src 'self' 'unsafe-inline' 'unsafe-eval' https://cse.google.com/ http://cse.google.com/adsense/search/async-ads.js https://www.google"], ["strict-transport-security", "max-age=31536000; preload"], ["accept-ranges", "bytes"], ["date", "Fri, 02 Jun 2023 23:47:03 GMT"], ["age", "1419"], ["x-served-by", "cache-hel1410024-HEL, cache-fra-etou8220042-FRA"], ["x-cache", "HIT, HIT"], ["x-cache-hits", "4, 1"], ["x-timer", "S1685749624.692627,VS0,VE1"], ["content-length", "30223"]], [["server", "Apache/2.4.29 (Ubuntu)"], ["last-modified", "Mon, 12 Aug 2019 09:32:05 GMT"], ["etag", "\"85bb-58fe83272763a\""], ["content-type", "image/png"], ["via", "1.1 www.apache.org, 1.1 varnish, 1.1 varnish"], ["cache-control", "max-age=3600"], ["expires", "Fri, 02 Jun 2023 20:23:17 GMT"], ["content-security-policy", "default-src 'self' 'unsafe-inline' https://www.apachecon.com/ https://www.google.com/cse/ https://cse.google.com/ https://www.googleapis.com/generate_204 http://*.google.com/generate_204 https://afs.googlesyndication.com/ https://csp.withgoogle.com/ https://www.google.com/images/ https://ssl.gstatic.com/ui/ https://docs.google.com/forms/ https://www.youtube.com/embed/; script-src 'self' 'unsafe-inline' 'unsafe-eval' https://cse.google.com/ http://cse.google.com/adsense/search/async-ads.js https://www.google"], ["strict-transport-security", "max-age=31536000; preload"], ["accept-ranges", "bytes"], ["date", "Fri, 02 Jun 2023 23:47:03 GMT"], ["age", "1419"], ["x-served-by", "cache-hel1410029-HEL, cache-fra-etou8220042-FRA"], ["x-cache", "HIT, HIT"], ["x-cache-hits", "2, 1"], ["x-timer", "S1685749624.674404,VS0,VE1"], ["content-length", "34235"]], [["content-type", "text/javascript; charset=UTF-8"], ["cross-origin-resource-policy", "cross-origin"], ["content-security-policy", "object-src 'none';base-uri 'self';script-src 'nonce-SpRYKdvmPNzPMADlgmEi1g' 'strict-dynamic' 'report-sample' 'unsafe-eval' 'unsafe-inline' https: http:;report-uri https://csp.withgoogle.com/csp/gws/other"], ["cross-origin-opener-policy", "same-origin-allow-popups; report-to=\"gws\""], ["report-to", "{\"group\":\"gws\",\"max_age\":2592000,\"endpoints\":[{\"url\":\"https://csp.withgoogle.com/csp/report-to/gws/other\"}]}"], ["accept-ch", "Sec-CH-UA-Platform"], ["accept-ch", "Sec-CH-UA-Platform"], ["accept-ch", "Sec-CH-UA-Platform"], ["accept-ch", "Sec-CH-UA-Platform"], ["accept-ch", "Sec-CH-UA-Platform"], ["accept-ch", "Sec-CH-UA-Platform"], ["accept-ch", "Sec-CH-UA-Platform"], ["accept-ch", "Sec-CH-UA-Platform"], ["permissions-policy", "unload=()"], ["origin-trial", "Ap+qNlnLzJDKSmEHjzM5ilaa908GuehlLqGb6ezME5lkhelj20qVzfv06zPmQ3LodoeujZuphAolrnhnPA8w4AIAAABfeyJvcmlnaW4iOiJodHRwczovL3d3dy5nb29nbGUuY29tOjQ0MyIsImZlYXR1cmUiOiJQZXJtaXNzaW9uc1BvbGljeVVubG9hZCIsImV4cGlyeSI6MTY4NTY2Mzk5OX0="], ["origin-trial", "Ap+qNlnLzJDKSmEHjzM5ilaa908GuehlLqGb6ezME5lkhelj20qVzfv06zPmQ3LodoeujZuphAolrnhnPA8w4AIAAABfeyJvcmlnaW4iOiJodHRwczovL3d3dy5nb29nbGUuY29tOjQ0MyIsImZlYXR1cmUiOiJQZXJtaXNzaW9uc1BvbGljeVVubG9hZCIsImV4cGlyeSI6MTY4NTY2Mzk5OX0="], ["content-disposition", "attachment; filename=\"f.txt\""], ["content-encoding", "gzip"], ["date", "Fri, 02 Jun 2023 23:47:04 GMT"], ["server", "gws"], ["cache-control", "private"], ["content-length", "3293"], ["x-xss-protection", "0"], ["x-frame-options", "SAMEORIGIN"], ["set-cookie", "CONSENT=PENDING+129; expires=Sun, 01-Jun-2025 23:47:04 GMT; path=/; domain=.google.com; Secure"], ["p3p", "CP=\"This is not a P3P policy! See g.co/p3phelp for more info.\""], ["alt-svc", "h3=\":443\"; ma=2592000,h3-29=\":443\"; ma=2592000"], ["expires", "Fri, 02 Jun 2023 23:47:04 GMT"]], [["server", "Apache"], ["last-modified", "Tue, 03 Jan 2023 14:18:22 GMT"], ["etag", "\"7ad8-5f15cbd87b27d\""], ["cache-control", "max-age=3600"], ["expires", "Fri, 05 May 2023 16:23:18 GMT"], ["content-security-policy", "default-src 'self' 'unsafe-inline' https://www.apachecon.com/ https://www.google.com/cse/ https://cse.google.com/ https://www.googleapis.com/generate_204 http://*.google.com/generate_204 https://afs.googlesyndication.com/ https://csp.withgoogle.com/ https://www.google.com/images/ https://ssl.gstatic.com/ui/ https://docs.google.com/forms/ https://www.youtube.com/embed/; script-src 'self' 'unsafe-inline' 'unsafe-eval' https://cse.google.com/ http://cse.google.com/adsense/search/async-ads.js https://www.google"], ["strict-transport-security", "max-age=31536000; preload"], ["content-type", "font/ttf"], ["content-encoding", "gzip"], ["via", "1.1 varnish, 1.1 varnish"], ["accept-ranges", "bytes"], ["date", "Fri, 02 Jun 2023 23:47:05 GMT"], ["age", "1423"], ["x-served-by", "cache-hel1410029-HEL, cache-fra-etou8220042-FRA"], ["x-cache", "HIT, HIT"], ["x-cache-hits", "5, 1"], ["x-timer", "S1685749625.227410,VS0,VE1"], ["vary", "Accept-Encoding"], ["content-length", "16374"]], [["server", "Apache"], ["last-modified", "Mon, 16 May 2022 19:23:08 GMT"], ["etag", "\"466c-5df25f4407a72\""], ["cache-control", "max-age=3600"], ["expires", "Tue, 14 Mar 2023 03:23:17 GMT"], ["content-security-policy", "default-src 'self' 'unsafe-inline' https://www.apachecon.com/ https://www.google.com/cse/ https://cse.google.com/ https://www.googleapis.com/generate_204 http://*.google.com/generate_204 https://afs.googlesyndication.com/ https://csp.withgoogle.com/ https://www.google.com/images/ https://ssl.gstatic.com/ui/ https://docs.google.com/forms/ https://www.youtube.com/embed/; script-src 'self' 'unsafe-inline' 'unsafe-eval' https://cse.google.com/ http://cse.google.com/adsense/search/async-ads.js https://www.google"], ["strict-transport-security", "max-age=31536000; preload"], ["content-type", "font/woff2"], ["via", "1.1 varnish, 1.1 varnish"], ["accept-ranges", "bytes"], ["date", "Fri, 02 Jun 2023 23:47:05 GMT"], ["age", "1419"], ["x-served-by", "cache-hel1410034-HEL, cache-fra-etou8220042-FRA"], ["x-cache", "HIT, HIT"], ["x-cache-hits", "5, 1"], ["x-timer", "S1685749625.255660,VS0,VE1"], ["content-length", "18028"]], [["server", "Apache"], ["last-modified", "Tue, 03 Jan 2023 14:18:22 GMT"], ["etag", "\"7af4-5f15cbd87b27d\""], ["cache-control", "max-age=3600"], ["expires", "Tue, 09 May 2023 03:23:18 GMT"], ["content-security-policy", "default-src 'self' 'unsafe-inline' https://www.apachecon.com/ https://www.google.com/cse/ https://cse.google.com/ https://www.googleapis.com/generate_204 http://*.google.com/generate_204 https://afs.googlesyndication.com/ https://csp.withgoogle.com/ https://www.google.com/images/ https://ssl.gstatic.com/ui/ https://docs.google.com/forms/ https://www.youtube.com/embed/; script-src 'self' 'unsafe-inline' 'unsafe-eval' https://cse.google.com/ http://cse.google.com/adsense/search/async-ads.js https://www.google"], ["strict-transport-security", "max-age=31536000; preload"], ["content-type", "font/ttf"], ["content-encoding", "gzip"], ["via", "1.1 varnish, 1.1 varnish"], ["accept-ranges", "bytes"], ["date", "Fri, 02 Jun 2023 23:47:05 GMT"], ["age", "1423"], ["x-served-by", "cache-hel1410031-HEL, cache-fra-etou8220042-FRA"], ["x-cache", "HIT, HIT"], ["x-cache-hits", "6, 1"], ["x-timer", "S1685749625.308181,VS0,VE1"], ["vary", "Accept-Encoding"], ["content-length", "16238"]], [["accept-ranges", "bytes"], ["content-encoding", "gzip"], ["content-security-policy-report-only", "require-trusted-types-for 'script'; report-uri https://csp.withgoogle.com/csp/prose-team"], ["cross-origin-resource-policy", "cross-origin"], ["cross-origin-opener-policy-report-only", "same-origin; report-to=\"prose-team\""], ["report-to", "{\"group\":\"prose-team\",\"max_age\":2592000,\"endpoints\":[{\"url\":\"https://csp.withgoogle.com/csp/report-to/prose-team\"}]}"], ["content-length", "9102"], ["x-content-type-options", "nosniff"], ["server", "sffe"], ["x-xss-protection", "0"], ["date", "Tue, 30 May 2023 21:36:09 GMT"], ["expires", "Wed, 29 May 2024 21:36:09 GMT"], ["cache-control", "public, max-age=31536000"], ["last-modified", "Fri, 26 May 2023 16:15:24 GMT"], ["content-type", "text/css"], ["vary", "Accept-Encoding"], ["age", "267057"], ["alt-svc", "h3=\":443\"; ma=2592000,h3-29=\":443\"; ma=2592000"]], [["accept-ranges", "bytes"], ["content-encoding", "gzip"], ["content-security-policy-report-only", "require-trusted-types-for 'script'; report-uri https://csp.withgoogle.com/csp/prose-team"], ["cross-origin-resource-policy", "cross-origin"], ["cross-origin-opener-policy-report-only", "same-origin; report-to=\"prose-team\""], ["report-to", "{\"group\":\"prose-team\",\"max_age\":2592000,\"endpoints\":[{\"url\":\"https://csp.withgoogle.com/csp/report-to/prose-team\"}]}"], ["content-length", "104753"], ["x-content-type-options", "nosniff"], ["server", "sffe"], ["x-xss-protection", "0"], ["date", "Tue, 30 May 2023 21:36:09 GMT"], ["expires", "Wed, 29 May 2024 21:36:09 GMT"], ["cache-control", "public, max-age=31536000"], ["last-modified", "Fri, 26 May 2023 16:15:24 GMT"], ["content-type", "text/javascript"], ["vary", "Accept-Encoding"], ["age", "267057"], ["alt-svc", "h3=\":443\"; ma=2592000,h3-29=\":443\"; ma=2592000"]], [["accept-ranges", "bytes"], ["content-encoding", "gzip"], ["content-security-policy-report-only", "require-trusted-types-for 'script'; report-uri https://csp.withgoogle.com/csp/prose-team"], ["cross-origin-resource-policy", "cross-origin"], ["cross-origin-opener-policy-report-only", "same-origin; report-to=\"prose-team\""], ["report-to", "{\"group\":\"prose-team\",\"max_age\":2592000,\"endpoints\":[{\"url\":\"https://csp.withgoogle.com/csp/report-to/prose-team\"}]}"], ["content-length", "1345"], ["x-content-type-options", "nosniff"], ["server", "sffe"], ["x-xss-protection", "0"], ["date", "Fri, 02 Jun 2023 23:08:41 GMT"], ["expires", "Fri, 02 Jun 2023 23:58:41 GMT"], ["cache-control", "public, max-age=3000"], ["age", "2305"], ["last-modified", "Wed, 17 Jun 2020 00:00:00 GMT"], ["content-type", "text/css"], ["vary", "Accept-Encoding"], ["alt-svc", "h3=\":443\"; ma=2592000,h3-29=\":443\"; ma=2592000"]], [["accept-ranges", "bytes"], ["vary", "Accept-Encoding"], ["content-type", "text/javascript; charset=UTF-8"], ["content-security-policy-report-only", "require-trusted-types-for 'script'; report-uri https://csp.withgoogle.com/csp/ads-afs-ui"], ["cross-origin-resource-policy", "cross-origin"], ["cross-origin-opener-policy", "same-origin; report-to=\"ads-afs-ui\""], ["report-to", "{\"group\":\"ads-afs-ui\",\"max_age\":2592000,\"endpoints\":[{\"url\":\"https://csp.withgoogle.com/csp/report-to/ads-afs-ui\"}]}"], ["date", "Fri, 02 Jun 2023 23:47:06 GMT"], ["expires", "Fri, 02 Jun 2023 23:47:06 GMT"], ["cache-control", "private, max-age=3600"], ["etag", "\"16203375810772363807\""], ["x-content-type-options", "nosniff"], ["content-encoding", "gzip"], ["server", "sffe"], ["x-xss-protection", "0"], ["alt-svc", "h3=\":443\"; ma=2592000,h3-29=\":443\"; ma=2592000"]], [["accept-ranges", "bytes"], ["content-security-policy-report-only", "require-trusted-types-for 'script'; report-uri https://csp.withgoogle.com/csp/prose-team"], ["cross-origin-resource-policy", "cross-origin"], ["cross-origin-opener-policy-report-only", "same-origin; report-to=\"prose-team\""], ["report-to", "{\"group\":\"prose-team\",\"max_age\":2592000,\"endpoints\":[{\"url\":\"https://csp.withgoogle.com/csp/report-to/prose-team\"}]}"], ["content-length", "1372"], ["x-content-type-options", "nosniff"], ["server", "sffe"], ["x-xss-protection", "0"], ["date", "Mon, 29 May 2023 20:32:32 GMT"], ["expires", "Tue, 28 May 2024 20:32:32 GMT"], ["cache-control", "public, max-age=31536000"], ["last-modified", "Mon, 25 May 2020 08:30:00 GMT"], ["content-type", "image/png"], ["age", "357274"], ["alt-svc", "h3=\":443\"; ma=2592000,h3-29=\":443\"; ma=2592000"]], [["content-length", "0"], ["cross-origin-resource-policy", "cross-origin"], ["date", "Fri, 02 Jun 2023 23:47:07 GMT"], ["alt-svc", "h3=\":443\"; ma=2592000,h3-29=\":443\"; ma=2592000"]]], "request_date": [1685749622796.306, 1685749623153.969, 1685749623346.069, 1685749623372.383, 1685749623373.816, 1685749623387.842, 1685749623400.263, 1685749623404.621, 1685749623409.666, 1685749623420.876, 1685749623426.334, 1685749623429.613, 1685749623451.01, 1685749623468.637, 1685749623483.959, 1685749623493.404, 1685749623609.834, 1685749623632.856, 1685749623648.829, 1685749623655.389, 1685749623656.894, 1685749624234.575, 1685749625211.235, 1685749625233.109, 1685749625290.614, 1685749626160.502, 1685749626190.195, 1685749626192.809, 1685749626600.965, 1685749626648.711, 1685749627079.399], "x_domain_redirects": [], "cookies": [], "third_party_request_domains": [], "third_party_response_domains": ["youtube.com", "gstatic.com", "apachecon.com", "www.google", "www.googleapis.com", "google.com", "csp.withgoogle.com", "googlesyndication.com"]}