{"domain": "networkadvertising.org", "pageload_start_ts": 1685760654.2965834, "pageload_end_ts": 1685760691.0848916, "post_pageload_url": "https://thenai.org/", "errors": {"page_load_timeout": 0, "dns": 0, "consent_click": null}, "tracker_domains": ["google-analytics.com"], "tracker_entities": ["http://www.google.com/"], "request_headers": [[["Host", "www.networkadvertising.org"], ["Proxy-Connection", "keep-alive"], ["Upgrade-Insecure-Requests", "1"], ["User-Agent", "Mozilla/5.0 (X11; Linux x86_64) AppleWebKit/537.36 (KHTML, like Gecko) HeadlessChrome/114.0.5735.90 Safari/537.36"], ["Accept", "text/html,application/xhtml+xml,application/xml;q=0.9,image/avif,image/webp,image/apng,*/*;q=0.8,application/signed-exchange;v=b3;q=0.7"], ["Accept-Encoding", "gzip, deflate"]], [["upgrade-insecure-requests", "1"], ["user-agent", "Mozilla/5.0 (X11; Linux x86_64) AppleWebKit/537.36 (KHTML, like Gecko) HeadlessChrome/114.0.5735.90 Safari/537.36"], ["accept", "text/html,application/xhtml+xml,application/xml;q=0.9,image/avif,image/webp,image/apng,*/*;q=0.8,application/signed-exchange;v=b3;q=0.7"], ["sec-fetch-site", "none"], ["sec-fetch-mode", "navigate"], ["sec-fetch-user", "?1"], ["sec-fetch-dest", "document"], ["sec-ch-ua", "\"Not.A/Brand\";v=\"8\", \"Chromium\";v=\"114\", \"HeadlessChrome\";v=\"114\""], ["sec-ch-ua-mobile", "?0"], ["sec-ch-ua-platform", "\"Linux\""], ["accept-encoding", "gzip, deflate, br"]], [["sec-ch-ua", "\"Not.A/Brand\";v=\"8\", \"Chromium\";v=\"114\", \"HeadlessChrome\";v=\"114\""], ["sec-ch-ua-mobile", "?0"], ["user-agent", "Mozilla/5.0 (X11; Linux x86_64) AppleWebKit/537.36 (KHTML, like Gecko) HeadlessChrome/114.0.5735.90 Safari/537.36"], ["sec-ch-ua-platform", "\"Linux\""], ["accept", "text/css,*/*;q=0.1"], ["sec-fetch-site", "same-origin"], ["sec-fetch-mode", "no-cors"], ["sec-fetch-dest", "style"], ["referer", "https://thenai.org/"], ["accept-encoding", "gzip, deflate, br"]], [["sec-ch-ua", "\"Not.A/Brand\";v=\"8\", \"Chromium\";v=\"114\", \"HeadlessChrome\";v=\"114\""], ["sec-ch-ua-mobile", "?0"], ["user-agent", "Mozilla/5.0 (X11; Linux x86_64) AppleWebKit/537.36 (KHTML, like Gecko) HeadlessChrome/114.0.5735.90 Safari/537.36"], ["sec-ch-ua-platform", "\"Linux\""], ["accept", "text/css,*/*;q=0.1"], ["sec-fetch-site", "same-origin"], ["sec-fetch-mode", "no-cors"], ["sec-fetch-dest", "style"], ["referer", "https://thenai.org/"], ["accept-encoding", "gzip, deflate, br"]], [["sec-ch-ua", "\"Not.A/Brand\";v=\"8\", \"Chromium\";v=\"114\", \"HeadlessChrome\";v=\"114\""], ["sec-ch-ua-mobile", "?0"], ["user-agent", "Mozilla/5.0 (X11; Linux x86_64) AppleWebKit/537.36 (KHTML, like Gecko) HeadlessChrome/114.0.5735.90 Safari/537.36"], ["sec-ch-ua-platform", "\"Linux\""], ["accept", "text/css,*/*;q=0.1"], ["sec-fetch-site", "same-origin"], ["sec-fetch-mode", "no-cors"], ["sec-fetch-dest", "style"], ["referer", "https://thenai.org/"], ["accept-encoding", "gzip, deflate, br"]], [["sec-ch-ua", "\"Not.A/Brand\";v=\"8\", \"Chromium\";v=\"114\", \"HeadlessChrome\";v=\"114\""], ["sec-ch-ua-mobile", "?0"], ["user-agent", "Mozilla/5.0 (X11; Linux x86_64) AppleWebKit/537.36 (KHTML, like Gecko) HeadlessChrome/114.0.5735.90 Safari/537.36"], ["sec-ch-ua-platform", "\"Linux\""], ["accept", "text/css,*/*;q=0.1"], ["sec-fetch-site", "same-origin"], ["sec-fetch-mode", "no-cors"], ["sec-fetch-dest", "style"], ["referer", "https://thenai.org/"], ["accept-encoding", "gzip, deflate, br"]], [["sec-ch-ua", "\"Not.A/Brand\";v=\"8\", \"Chromium\";v=\"114\", \"HeadlessChrome\";v=\"114\""], ["sec-ch-ua-mobile", "?0"], ["user-agent", "Mozilla/5.0 (X11; Linux x86_64) AppleWebKit/537.36 (KHTML, like Gecko) HeadlessChrome/114.0.5735.90 Safari/537.36"], ["sec-ch-ua-platform", "\"Linux\""], ["accept", "*/*"], ["sec-fetch-site", "same-origin"], ["sec-fetch-mode", "no-cors"], ["sec-fetch-dest", "script"], ["referer", "https://thenai.org/"], ["accept-encoding", "gzip, deflate, br"]], [["sec-ch-ua", "\"Not.A/Brand\";v=\"8\", \"Chromium\";v=\"114\", \"HeadlessChrome\";v=\"114\""], ["sec-ch-ua-mobile", "?0"], ["user-agent", "Mozilla/5.0 (X11; Linux x86_64) AppleWebKit/537.36 (KHTML, like Gecko) HeadlessChrome/114.0.5735.90 Safari/537.36"], ["sec-ch-ua-platform", "\"Linux\""], ["accept", "*/*"], ["sec-fetch-site", "same-origin"], ["sec-fetch-mode", "no-cors"], ["sec-fetch-dest", "script"], ["referer", "https://thenai.org/"], ["accept-encoding", "gzip, deflate, br"]], [["sec-ch-ua", "\"Not.A/Brand\";v=\"8\", \"Chromium\";v=\"114\", \"HeadlessChrome\";v=\"114\""], ["sec-ch-ua-mobile", "?0"], ["user-agent", "Mozilla/5.0 (X11; Linux x86_64) AppleWebKit/537.36 (KHTML, like Gecko) HeadlessChrome/114.0.5735.90 Safari/537.36"], ["sec-ch-ua-platform", "\"Linux\""], ["accept", "text/css,*/*;q=0.1"], ["sec-fetch-site", "cross-site"], ["sec-fetch-mode", "no-cors"], ["sec-fetch-dest", "style"], ["referer", "https://thenai.org/"], ["accept-encoding", "gzip, deflate, br"]], [["sec-ch-ua", "\"Not.A/Brand\";v=\"8\", \"Chromium\";v=\"114\", \"HeadlessChrome\";v=\"114\""], ["sec-ch-ua-mobile", "?0"], ["user-agent", "Mozilla/5.0 (X11; Linux x86_64) AppleWebKit/537.36 (KHTML, like Gecko) HeadlessChrome/114.0.5735.90 Safari/537.36"], ["sec-ch-ua-platform", "\"Linux\""], ["accept", "*/*"], ["sec-fetch-site", "same-origin"], ["sec-fetch-mode", "no-cors"], ["sec-fetch-dest", "script"], ["referer", "https://thenai.org/"], ["accept-encoding", "gzip, deflate, br"]], [["sec-ch-ua", "\"Not.A/Brand\";v=\"8\", \"Chromium\";v=\"114\", \"HeadlessChrome\";v=\"114\""], ["sec-ch-ua-mobile", "?0"], ["user-agent", "Mozilla/5.0 (X11; Linux x86_64) AppleWebKit/537.36 (KHTML, like Gecko) HeadlessChrome/114.0.5735.90 Safari/537.36"], ["sec-ch-ua-platform", "\"Linux\""], ["accept", "*/*"], ["sec-fetch-site", "same-origin"], ["sec-fetch-mode", "no-cors"], ["sec-fetch-dest", "script"], ["referer", "https://thenai.org/"], ["accept-encoding", "gzip, deflate, br"]], [["sec-ch-ua", "\"Not.A/Brand\";v=\"8\", \"Chromium\";v=\"114\", \"HeadlessChrome\";v=\"114\""], ["sec-ch-ua-mobile", "?0"], ["user-agent", "Mozilla/5.0 (X11; Linux x86_64) AppleWebKit/537.36 (KHTML, like Gecko) HeadlessChrome/114.0.5735.90 Safari/537.36"], ["sec-ch-ua-platform", "\"Linux\""], ["accept", "text/css,*/*;q=0.1"], ["sec-fetch-site", "cross-site"], ["sec-fetch-mode", "no-cors"], ["sec-fetch-dest", "style"], ["referer", "https://use.typekit.net/"], ["accept-encoding", "gzip, deflate, br"]], [["sec-ch-ua", "\"Not.A/Brand\";v=\"8\", \"Chromium\";v=\"114\", \"HeadlessChrome\";v=\"114\""], ["sec-ch-ua-mobile", "?0"], ["user-agent", "Mozilla/5.0 (X11; Linux x86_64) AppleWebKit/537.36 (KHTML, like Gecko) HeadlessChrome/114.0.5735.90 Safari/537.36"], ["sec-ch-ua-platform", "\"Linux\""], ["accept", "*/*"], ["sec-fetch-site", "same-origin"], ["sec-fetch-mode", "no-cors"], ["sec-fetch-dest", "script"], ["referer", "https://thenai.org/"], ["accept-encoding", "gzip, deflate, br"]], [["sec-ch-ua", "\"Not.A/Brand\";v=\"8\", \"Chromium\";v=\"114\", \"HeadlessChrome\";v=\"114\""], ["sec-ch-ua-mobile", "?0"], ["user-agent", "Mozilla/5.0 (X11; Linux x86_64) AppleWebKit/537.36 (KHTML, like Gecko) HeadlessChrome/114.0.5735.90 Safari/537.36"], ["sec-ch-ua-platform", "\"Linux\""], ["accept", "image/avif,image/webp,image/apng,image/svg+xml,image/*,*/*;q=0.8"], ["sec-fetch-site", "same-origin"], ["sec-fetch-mode", "no-cors"], ["sec-fetch-dest", "image"], ["referer", "https://thenai.org/"], ["accept-encoding", "gzip, deflate, br"]], [["sec-ch-ua", "\"Not.A/Brand\";v=\"8\", \"Chromium\";v=\"114\", \"HeadlessChrome\";v=\"114\""], ["sec-ch-ua-mobile", "?0"], ["user-agent", "Mozilla/5.0 (X11; Linux x86_64) AppleWebKit/537.36 (KHTML, like Gecko) HeadlessChrome/114.0.5735.90 Safari/537.36"], ["sec-ch-ua-platform", "\"Linux\""], ["accept", "image/avif,image/webp,image/apng,image/svg+xml,image/*,*/*;q=0.8"], ["sec-fetch-site", "same-origin"], ["sec-fetch-mode", "no-cors"], ["sec-fetch-dest", "image"], ["referer", "https://thenai.org/"], ["accept-encoding", "gzip, deflate, br"]], [["sec-ch-ua", "\"Not.A/Brand\";v=\"8\", \"Chromium\";v=\"114\", \"HeadlessChrome\";v=\"114\""], ["sec-ch-ua-mobile", "?0"], ["user-agent", "Mozilla/5.0 (X11; Linux x86_64) AppleWebKit/537.36 (KHTML, like Gecko) HeadlessChrome/114.0.5735.90 Safari/537.36"], ["sec-ch-ua-platform", "\"Linux\""], ["accept", "image/avif,image/webp,image/apng,image/svg+xml,image/*,*/*;q=0.8"], ["sec-fetch-site", "same-origin"], ["sec-fetch-mode", "no-cors"], ["sec-fetch-dest", "image"], ["referer", "https://thenai.org/"], ["accept-encoding", "gzip, deflate, br"]], [["sec-ch-ua", "\"Not.A/Brand\";v=\"8\", \"Chromium\";v=\"114\", \"HeadlessChrome\";v=\"114\""], ["sec-ch-ua-mobile", "?0"], ["user-agent", "Mozilla/5.0 (X11; Linux x86_64) AppleWebKit/537.36 (KHTML, like Gecko) HeadlessChrome/114.0.5735.90 Safari/537.36"], ["sec-ch-ua-platform", "\"Linux\""], ["accept", "*/*"], ["sec-fetch-site", "cross-site"], ["sec-fetch-mode", "no-cors"], ["sec-fetch-dest", "script"], ["referer", "https://thenai.org/"], ["accept-encoding", "gzip, deflate, br"]], [["sec-ch-ua", "\"Not.A/Brand\";v=\"8\", \"Chromium\";v=\"114\", \"HeadlessChrome\";v=\"114\""], ["sec-ch-ua-mobile", "?0"], ["user-agent", "Mozilla/5.0 (X11; Linux x86_64) AppleWebKit/537.36 (KHTML, like Gecko) HeadlessChrome/114.0.5735.90 Safari/537.36"], ["sec-ch-ua-platform", "\"Linux\""], ["accept", "image/avif,image/webp,image/apng,image/svg+xml,image/*,*/*;q=0.8"], ["sec-fetch-site", "same-origin"], ["sec-fetch-mode", "no-cors"], ["sec-fetch-dest", "image"], ["referer", "https://thenai.org/"], ["accept-encoding", "gzip, deflate, br"]], [["sec-ch-ua", "\"Not.A/Brand\";v=\"8\", \"Chromium\";v=\"114\", \"HeadlessChrome\";v=\"114\""], ["sec-ch-ua-mobile", "?0"], ["user-agent", "Mozilla/5.0 (X11; Linux x86_64) AppleWebKit/537.36 (KHTML, like Gecko) HeadlessChrome/114.0.5735.90 Safari/537.36"], ["sec-ch-ua-platform", "\"Linux\""], ["accept", "image/avif,image/webp,image/apng,image/svg+xml,image/*,*/*;q=0.8"], ["sec-fetch-site", "same-origin"], ["sec-fetch-mode", "no-cors"], ["sec-fetch-dest", "image"], ["referer", "https://thenai.org/"], ["accept-encoding", "gzip, deflate, br"]], [["sec-ch-ua", "\"Not.A/Brand\";v=\"8\", \"Chromium\";v=\"114\", \"HeadlessChrome\";v=\"114\""], ["sec-ch-ua-mobile", "?0"], ["user-agent", "Mozilla/5.0 (X11; Linux x86_64) AppleWebKit/537.36 (KHTML, like Gecko) HeadlessChrome/114.0.5735.90 Safari/537.36"], ["sec-ch-ua-platform", "\"Linux\""], ["accept", "image/avif,image/webp,image/apng,image/svg+xml,image/*,*/*;q=0.8"], ["sec-fetch-site", "same-origin"], ["sec-fetch-mode", "no-cors"], ["sec-fetch-dest", "image"], ["referer", "https://thenai.org/"], ["accept-encoding", "gzip, deflate, br"]], [["sec-ch-ua", "\"Not.A/Brand\";v=\"8\", \"Chromium\";v=\"114\", \"HeadlessChrome\";v=\"114\""], ["sec-ch-ua-mobile", "?0"], ["user-agent", "Mozilla/5.0 (X11; Linux x86_64) AppleWebKit/537.36 (KHTML, like Gecko) HeadlessChrome/114.0.5735.90 Safari/537.36"], ["sec-ch-ua-platform", "\"Linux\""], ["accept", "image/avif,image/webp,image/apng,image/svg+xml,image/*,*/*;q=0.8"], ["sec-fetch-site", "same-origin"], ["sec-fetch-mode", "no-cors"], ["sec-fetch-dest", "image"], ["referer", "https://thenai.org/"], ["accept-encoding", "gzip, deflate, br"]], [["sec-ch-ua", "\"Not.A/Brand\";v=\"8\", \"Chromium\";v=\"114\", \"HeadlessChrome\";v=\"114\""], ["sec-ch-ua-mobile", "?0"], ["user-agent", "Mozilla/5.0 (X11; Linux x86_64) AppleWebKit/537.36 (KHTML, like Gecko) HeadlessChrome/114.0.5735.90 Safari/537.36"], ["sec-ch-ua-platform", "\"Linux\""], ["accept", "image/avif,image/webp,image/apng,image/svg+xml,image/*,*/*;q=0.8"], ["sec-fetch-site", "same-origin"], ["sec-fetch-mode", "no-cors"], ["sec-fetch-dest", "image"], ["referer", "https://thenai.org/"], ["accept-encoding", "gzip, deflate, br"]], [["sec-ch-ua", "\"Not.A/Brand\";v=\"8\", \"Chromium\";v=\"114\", \"HeadlessChrome\";v=\"114\""], ["sec-ch-ua-mobile", "?0"], ["user-agent", "Mozilla/5.0 (X11; Linux x86_64) AppleWebKit/537.36 (KHTML, like Gecko) HeadlessChrome/114.0.5735.90 Safari/537.36"], ["sec-ch-ua-platform", "\"Linux\""], ["accept", "*/*"], ["sec-fetch-site", "cross-site"], ["sec-fetch-mode", "no-cors"], ["sec-fetch-dest", "script"], ["referer", "https://thenai.org/"], ["accept-encoding", "gzip, deflate, br"]], [["sec-ch-ua", "\"Not.A/Brand\";v=\"8\", \"Chromium\";v=\"114\", \"HeadlessChrome\";v=\"114\""], ["sec-ch-ua-mobile", "?0"], ["user-agent", "Mozilla/5.0 (X11; Linux x86_64) AppleWebKit/537.36 (KHTML, like Gecko) HeadlessChrome/114.0.5735.90 Safari/537.36"], ["sec-ch-ua-platform", "\"Linux\""], ["accept", "image/avif,image/webp,image/apng,image/svg+xml,image/*,*/*;q=0.8"], ["sec-fetch-site", "same-origin"], ["sec-fetch-mode", "no-cors"], ["sec-fetch-dest", "image"], ["referer", "https://thenai.org/"], ["accept-encoding", "gzip, deflate, br"]], [["sec-ch-ua", "\"Not.A/Brand\";v=\"8\", \"Chromium\";v=\"114\", \"HeadlessChrome\";v=\"114\""], ["sec-ch-ua-mobile", "?0"], ["user-agent", "Mozilla/5.0 (X11; Linux x86_64) AppleWebKit/537.36 (KHTML, like Gecko) HeadlessChrome/114.0.5735.90 Safari/537.36"], ["sec-ch-ua-platform", "\"Linux\""], ["accept", "image/avif,image/webp,image/apng,image/svg+xml,image/*,*/*;q=0.8"], ["sec-fetch-site", "same-origin"], ["sec-fetch-mode", "no-cors"], ["sec-fetch-dest", "image"], ["referer", "https://thenai.org/"], ["accept-encoding", "gzip, deflate, br"]], [["sec-ch-ua", "\"Not.A/Brand\";v=\"8\", \"Chromium\";v=\"114\", \"HeadlessChrome\";v=\"114\""], ["sec-ch-ua-mobile", "?0"], ["user-agent", "Mozilla/5.0 (X11; Linux x86_64) AppleWebKit/537.36 (KHTML, like Gecko) HeadlessChrome/114.0.5735.90 Safari/537.36"], ["sec-ch-ua-platform", "\"Linux\""], ["accept", "image/avif,image/webp,image/apng,image/svg+xml,image/*,*/*;q=0.8"], ["sec-fetch-site", "same-origin"], ["sec-fetch-mode", "no-cors"], ["sec-fetch-dest", "image"], ["referer", "https://thenai.org/"], ["accept-encoding", "gzip, deflate, br"]], [["sec-ch-ua", "\"Not.A/Brand\";v=\"8\", \"Chromium\";v=\"114\", \"HeadlessChrome\";v=\"114\""], ["sec-ch-ua-mobile", "?0"], ["user-agent", "Mozilla/5.0 (X11; Linux x86_64) AppleWebKit/537.36 (KHTML, like Gecko) HeadlessChrome/114.0.5735.90 Safari/537.36"], ["sec-ch-ua-platform", "\"Linux\""], ["accept", "image/avif,image/webp,image/apng,image/svg+xml,image/*,*/*;q=0.8"], ["sec-fetch-site", "same-origin"], ["sec-fetch-mode", "no-cors"], ["sec-fetch-dest", "image"], ["referer", "https://thenai.org/"], ["accept-encoding", "gzip, deflate, br"]], [["sec-ch-ua", "\"Not.A/Brand\";v=\"8\", \"Chromium\";v=\"114\", \"HeadlessChrome\";v=\"114\""], ["origin", "https://thenai.org"], ["sec-ch-ua-mobile", "?0"], ["user-agent", "Mozilla/5.0 (X11; Linux x86_64) AppleWebKit/537.36 (KHTML, like Gecko) HeadlessChrome/114.0.5735.90 Safari/537.36"], ["sec-ch-ua-platform", "\"Linux\""], ["accept", "*/*"], ["sec-fetch-site", "same-origin"], ["sec-fetch-mode", "cors"], ["sec-fetch-dest", "font"], ["referer", "https://thenai.org/wp-content/themes/nai/public/styles/app.css?id=625fdbe70abaf48e7d31"], ["accept-encoding", "gzip, deflate, br"]], [["sec-ch-ua", "\"Not.A/Brand\";v=\"8\", \"Chromium\";v=\"114\", \"HeadlessChrome\";v=\"114\""], ["sec-ch-ua-mobile", "?0"], ["sec-ch-ua-platform", "\"Linux\""], ["upgrade-insecure-requests", "1"], ["user-agent", "Mozilla/5.0 (X11; Linux x86_64) AppleWebKit/537.36 (KHTML, like Gecko) HeadlessChrome/114.0.5735.90 Safari/537.36"], ["accept", "text/html,application/xhtml+xml,application/xml;q=0.9,image/avif,image/webp,image/apng,*/*;q=0.8,application/signed-exchange;v=b3;q=0.7"], ["sec-fetch-site", "cross-site"], ["sec-fetch-mode", "navigate"], ["sec-fetch-dest", "iframe"], ["referer", "https://thenai.org/"], ["accept-encoding", "gzip, deflate, br"]], [["sec-ch-ua", "\"Not.A/Brand\";v=\"8\", \"Chromium\";v=\"114\", \"HeadlessChrome\";v=\"114\""], ["sec-ch-ua-mobile", "?0"], ["user-agent", "Mozilla/5.0 (X11; Linux x86_64) AppleWebKit/537.36 (KHTML, like Gecko) HeadlessChrome/114.0.5735.90 Safari/537.36"], ["sec-ch-ua-platform", "\"Linux\""], ["accept", "image/avif,image/webp,image/apng,image/svg+xml,image/*,*/*;q=0.8"], ["sec-fetch-site", "same-origin"], ["sec-fetch-mode", "no-cors"], ["sec-fetch-dest", "image"], ["referer", "https://thenai.org/"], ["accept-encoding", "gzip, deflate, br"]], [["sec-ch-ua", "\"Not.A/Brand\";v=\"8\", \"Chromium\";v=\"114\", \"HeadlessChrome\";v=\"114\""], ["origin", "https://thenai.org"], ["sec-ch-ua-mobile", "?0"], ["user-agent", "Mozilla/5.0 (X11; Linux x86_64) AppleWebKit/537.36 (KHTML, like Gecko) HeadlessChrome/114.0.5735.90 Safari/537.36"], ["sec-ch-ua-platform", "\"Linux\""], ["accept", "*/*"], ["sec-fetch-site", "cross-site"], ["sec-fetch-mode", "cors"], ["sec-fetch-dest", "script"], ["referer", "https://thenai.org/"], ["accept-encoding", "gzip, deflate, br"]], [["sec-ch-ua", "\"Not.A/Brand\";v=\"8\", \"Chromium\";v=\"114\", \"HeadlessChrome\";v=\"114\""], ["sec-ch-ua-mobile", "?0"], ["user-agent", "Mozilla/5.0 (X11; Linux x86_64) AppleWebKit/537.36 (KHTML, like Gecko) HeadlessChrome/114.0.5735.90 Safari/537.36"], ["sec-ch-ua-platform", "\"Linux\""], ["accept", "image/avif,image/webp,image/apng,image/svg+xml,image/*,*/*;q=0.8"], ["sec-fetch-site", "same-origin"], ["sec-fetch-mode", "no-cors"], ["sec-fetch-dest", "image"], ["referer", "https://thenai.org/"], ["accept-encoding", "gzip, deflate, br"]], [["sec-ch-ua", "\"Not.A/Brand\";v=\"8\", \"Chromium\";v=\"114\", \"HeadlessChrome\";v=\"114\""], ["sec-ch-ua-mobile", "?0"], ["user-agent", "Mozilla/5.0 (X11; Linux x86_64) AppleWebKit/537.36 (KHTML, like Gecko) HeadlessChrome/114.0.5735.90 Safari/537.36"], ["sec-ch-ua-platform", "\"Linux\""], ["accept", "image/avif,image/webp,image/apng,image/svg+xml,image/*,*/*;q=0.8"], ["sec-fetch-site", "same-origin"], ["sec-fetch-mode", "no-cors"], ["sec-fetch-dest", "image"], ["referer", "https://thenai.org/"], ["accept-encoding", "gzip, deflate, br"]], [["sec-ch-ua", "\"Not.A/Brand\";v=\"8\", \"Chromium\";v=\"114\", \"HeadlessChrome\";v=\"114\""], ["sec-ch-ua-mobile", "?0"], ["user-agent", "Mozilla/5.0 (X11; Linux x86_64) AppleWebKit/537.36 (KHTML, like Gecko) HeadlessChrome/114.0.5735.90 Safari/537.36"], ["sec-ch-ua-platform", "\"Linux\""], ["accept", "image/avif,image/webp,image/apng,image/svg+xml,image/*,*/*;q=0.8"], ["sec-fetch-site", "same-origin"], ["sec-fetch-mode", "no-cors"], ["sec-fetch-dest", "image"], ["referer", "https://thenai.org/"], ["accept-encoding", "gzip, deflate, br"]], [["sec-ch-ua", "\"Not.A/Brand\";v=\"8\", \"Chromium\";v=\"114\", \"HeadlessChrome\";v=\"114\""], ["sec-ch-ua-mobile", "?0"], ["user-agent", "Mozilla/5.0 (X11; Linux x86_64) AppleWebKit/537.36 (KHTML, like Gecko) HeadlessChrome/114.0.5735.90 Safari/537.36"], ["sec-ch-ua-platform", "\"Linux\""], ["accept", "image/avif,image/webp,image/apng,image/svg+xml,image/*,*/*;q=0.8"], ["sec-fetch-site", "same-origin"], ["sec-fetch-mode", "no-cors"], ["sec-fetch-dest", "image"], ["referer", "https://thenai.org/"], ["accept-encoding", "gzip, deflate, br"]], [["sec-ch-ua", "\"Not.A/Brand\";v=\"8\", \"Chromium\";v=\"114\", \"HeadlessChrome\";v=\"114\""], ["sec-ch-ua-mobile", "?0"], ["user-agent", "Mozilla/5.0 (X11; Linux x86_64) AppleWebKit/537.36 (KHTML, like Gecko) HeadlessChrome/114.0.5735.90 Safari/537.36"], ["sec-ch-ua-platform", "\"Linux\""], ["accept", "image/avif,image/webp,image/apng,image/svg+xml,image/*,*/*;q=0.8"], ["sec-fetch-site", "same-origin"], ["sec-fetch-mode", "no-cors"], ["sec-fetch-dest", "image"], ["referer", "https://thenai.org/"], ["accept-encoding", "gzip, deflate, br"]], [["sec-ch-ua", "\"Not.A/Brand\";v=\"8\", \"Chromium\";v=\"114\", \"HeadlessChrome\";v=\"114\""], ["sec-ch-ua-mobile", "?0"], ["user-agent", "Mozilla/5.0 (X11; Linux x86_64) AppleWebKit/537.36 (KHTML, like Gecko) HeadlessChrome/114.0.5735.90 Safari/537.36"], ["sec-ch-ua-platform", "\"Linux\""], ["accept", "image/avif,image/webp,image/apng,image/svg+xml,image/*,*/*;q=0.8"], ["sec-fetch-site", "same-origin"], ["sec-fetch-mode", "no-cors"], ["sec-fetch-dest", "image"], ["referer", "https://thenai.org/"], ["accept-encoding", "gzip, deflate, br"]], [["sec-ch-ua", "\"Not.A/Brand\";v=\"8\", \"Chromium\";v=\"114\", \"HeadlessChrome\";v=\"114\""], ["sec-ch-ua-mobile", "?0"], ["user-agent", "Mozilla/5.0 (X11; Linux x86_64) AppleWebKit/537.36 (KHTML, like Gecko) HeadlessChrome/114.0.5735.90 Safari/537.36"], ["sec-ch-ua-platform", "\"Linux\""], ["accept", "image/avif,image/webp,image/apng,image/svg+xml,image/*,*/*;q=0.8"], ["sec-fetch-site", "same-origin"], ["sec-fetch-mode", "no-cors"], ["sec-fetch-dest", "image"], ["referer", "https://thenai.org/"], ["accept-encoding", "gzip, deflate, br"]], [["sec-ch-ua", "\"Not.A/Brand\";v=\"8\", \"Chromium\";v=\"114\", \"HeadlessChrome\";v=\"114\""], ["sec-ch-ua-mobile", "?0"], ["user-agent", "Mozilla/5.0 (X11; Linux x86_64) AppleWebKit/537.36 (KHTML, like Gecko) HeadlessChrome/114.0.5735.90 Safari/537.36"], ["sec-ch-ua-platform", "\"Linux\""], ["accept", "image/avif,image/webp,image/apng,image/svg+xml,image/*,*/*;q=0.8"], ["sec-fetch-site", "same-origin"], ["sec-fetch-mode", "no-cors"], ["sec-fetch-dest", "image"], ["referer", "https://thenai.org/"], ["accept-encoding", "gzip, deflate, br"]], [["sec-ch-ua", "\"Not.A/Brand\";v=\"8\", \"Chromium\";v=\"114\", \"HeadlessChrome\";v=\"114\""], ["sec-ch-ua-mobile", "?0"], ["user-agent", "Mozilla/5.0 (X11; Linux x86_64) AppleWebKit/537.36 (KHTML, like Gecko) HeadlessChrome/114.0.5735.90 Safari/537.36"], ["sec-ch-ua-platform", "\"Linux\""], ["accept", "image/avif,image/webp,image/apng,image/svg+xml,image/*,*/*;q=0.8"], ["sec-fetch-site", "same-origin"], ["sec-fetch-mode", "no-cors"], ["sec-fetch-dest", "image"], ["referer", "https://thenai.org/"], ["accept-encoding", "gzip, deflate, br"]], [["sec-ch-ua", "\"Not.A/Brand\";v=\"8\", \"Chromium\";v=\"114\", \"HeadlessChrome\";v=\"114\""], ["sec-ch-ua-mobile", "?0"], ["user-agent", "Mozilla/5.0 (X11; Linux x86_64) AppleWebKit/537.36 (KHTML, like Gecko) HeadlessChrome/114.0.5735.90 Safari/537.36"], ["sec-ch-ua-platform", "\"Linux\""], ["accept", "image/avif,image/webp,image/apng,image/svg+xml,image/*,*/*;q=0.8"], ["sec-fetch-site", "same-origin"], ["sec-fetch-mode", "no-cors"], ["sec-fetch-dest", "image"], ["referer", "https://thenai.org/"], ["accept-encoding", "gzip, deflate, br"]], [["sec-ch-ua", "\"Not.A/Brand\";v=\"8\", \"Chromium\";v=\"114\", \"HeadlessChrome\";v=\"114\""], ["sec-ch-ua-mobile", "?0"], ["user-agent", "Mozilla/5.0 (X11; Linux x86_64) AppleWebKit/537.36 (KHTML, like Gecko) HeadlessChrome/114.0.5735.90 Safari/537.36"], ["sec-ch-ua-platform", "\"Linux\""], ["accept", "image/avif,image/webp,image/apng,image/svg+xml,image/*,*/*;q=0.8"], ["sec-fetch-site", "same-origin"], ["sec-fetch-mode", "no-cors"], ["sec-fetch-dest", "image"], ["referer", "https://thenai.org/"], ["accept-encoding", "gzip, deflate, br"]], [["sec-ch-ua", "\"Not.A/Brand\";v=\"8\", \"Chromium\";v=\"114\", \"HeadlessChrome\";v=\"114\""], ["sec-ch-ua-mobile", "?0"], ["user-agent", "Mozilla/5.0 (X11; Linux x86_64) AppleWebKit/537.36 (KHTML, like Gecko) HeadlessChrome/114.0.5735.90 Safari/537.36"], ["sec-ch-ua-platform", "\"Linux\""], ["accept", "image/avif,image/webp,image/apng,image/svg+xml,image/*,*/*;q=0.8"], ["sec-fetch-site", "same-origin"], ["sec-fetch-mode", "no-cors"], ["sec-fetch-dest", "image"], ["referer", "https://thenai.org/"], ["accept-encoding", "gzip, deflate, br"]], [["sec-ch-ua", "\"Not.A/Brand\";v=\"8\", \"Chromium\";v=\"114\", \"HeadlessChrome\";v=\"114\""], ["sec-ch-ua-mobile", "?0"], ["user-agent", "Mozilla/5.0 (X11; Linux x86_64) AppleWebKit/537.36 (KHTML, like Gecko) HeadlessChrome/114.0.5735.90 Safari/537.36"], ["sec-ch-ua-platform", "\"Linux\""], ["accept", "image/avif,image/webp,image/apng,image/svg+xml,image/*,*/*;q=0.8"], ["sec-fetch-site", "same-origin"], ["sec-fetch-mode", "no-cors"], ["sec-fetch-dest", "image"], ["referer", "https://thenai.org/"], ["accept-encoding", "gzip, deflate, br"]], [["sec-ch-ua", "\"Not.A/Brand\";v=\"8\", \"Chromium\";v=\"114\", \"HeadlessChrome\";v=\"114\""], ["sec-ch-ua-mobile", "?0"], ["user-agent", "Mozilla/5.0 (X11; Linux x86_64) AppleWebKit/537.36 (KHTML, like Gecko) HeadlessChrome/114.0.5735.90 Safari/537.36"], ["sec-ch-ua-platform", "\"Linux\""], ["accept", "image/avif,image/webp,image/apng,image/svg+xml,image/*,*/*;q=0.8"], ["sec-fetch-site", "same-origin"], ["sec-fetch-mode", "no-cors"], ["sec-fetch-dest", "image"], ["referer", "https://thenai.org/"], ["accept-encoding", "gzip, deflate, br"]], [["sec-ch-ua", "\"Not.A/Brand\";v=\"8\", \"Chromium\";v=\"114\", \"HeadlessChrome\";v=\"114\""], ["sec-ch-ua-mobile", "?0"], ["user-agent", "Mozilla/5.0 (X11; Linux x86_64) AppleWebKit/537.36 (KHTML, like Gecko) HeadlessChrome/114.0.5735.90 Safari/537.36"], ["sec-ch-ua-platform", "\"Linux\""], ["accept", "image/avif,image/webp,image/apng,image/svg+xml,image/*,*/*;q=0.8"], ["sec-fetch-site", "same-origin"], ["sec-fetch-mode", "no-cors"], ["sec-fetch-dest", "image"], ["referer", "https://thenai.org/"], ["accept-encoding", "gzip, deflate, br"]], [["sec-ch-ua", "\"Not.A/Brand\";v=\"8\", \"Chromium\";v=\"114\", \"HeadlessChrome\";v=\"114\""], ["sec-ch-ua-mobile", "?0"], ["user-agent", "Mozilla/5.0 (X11; Linux x86_64) AppleWebKit/537.36 (KHTML, like Gecko) HeadlessChrome/114.0.5735.90 Safari/537.36"], ["sec-ch-ua-platform", "\"Linux\""], ["accept", "image/avif,image/webp,image/apng,image/svg+xml,image/*,*/*;q=0.8"], ["sec-fetch-site", "same-origin"], ["sec-fetch-mode", "no-cors"], ["sec-fetch-dest", "image"], ["referer", "https://thenai.org/"], ["accept-encoding", "gzip, deflate, br"]], [["sec-ch-ua", "\"Not.A/Brand\";v=\"8\", \"Chromium\";v=\"114\", \"HeadlessChrome\";v=\"114\""], ["sec-ch-ua-mobile", "?0"], ["user-agent", "Mozilla/5.0 (X11; Linux x86_64) AppleWebKit/537.36 (KHTML, like Gecko) HeadlessChrome/114.0.5735.90 Safari/537.36"], ["sec-ch-ua-platform", "\"Linux\""], ["accept", "image/avif,image/webp,image/apng,image/svg+xml,image/*,*/*;q=0.8"], ["sec-fetch-site", "same-origin"], ["sec-fetch-mode", "no-cors"], ["sec-fetch-dest", "image"], ["referer", "https://thenai.org/"], ["accept-encoding", "gzip, deflate, br"]], [["sec-ch-ua", "\"Not.A/Brand\";v=\"8\", \"Chromium\";v=\"114\", \"HeadlessChrome\";v=\"114\""], ["sec-ch-ua-mobile", "?0"], ["user-agent", "Mozilla/5.0 (X11; Linux x86_64) AppleWebKit/537.36 (KHTML, like Gecko) HeadlessChrome/114.0.5735.90 Safari/537.36"], ["sec-ch-ua-platform", "\"Linux\""], ["accept", "image/avif,image/webp,image/apng,image/svg+xml,image/*,*/*;q=0.8"], ["sec-fetch-site", "same-origin"], ["sec-fetch-mode", "no-cors"], ["sec-fetch-dest", "image"], ["referer", "https://thenai.org/"], ["accept-encoding", "gzip, deflate, br"]], [["sec-ch-ua", "\"Not.A/Brand\";v=\"8\", \"Chromium\";v=\"114\", \"HeadlessChrome\";v=\"114\""], ["sec-ch-ua-mobile", "?0"], ["user-agent", "Mozilla/5.0 (X11; Linux x86_64) AppleWebKit/537.36 (KHTML, like Gecko) HeadlessChrome/114.0.5735.90 Safari/537.36"], ["sec-ch-ua-platform", "\"Linux\""], ["accept", "image/avif,image/webp,image/apng,image/svg+xml,image/*,*/*;q=0.8"], ["sec-fetch-site", "same-origin"], ["sec-fetch-mode", "no-cors"], ["sec-fetch-dest", "image"], ["referer", "https://thenai.org/"], ["accept-encoding", "gzip, deflate, br"]], [["sec-ch-ua", "\"Not.A/Brand\";v=\"8\", \"Chromium\";v=\"114\", \"HeadlessChrome\";v=\"114\""], ["sec-ch-ua-mobile", "?0"], ["user-agent", "Mozilla/5.0 (X11; Linux x86_64) AppleWebKit/537.36 (KHTML, like Gecko) HeadlessChrome/114.0.5735.90 Safari/537.36"], ["sec-ch-ua-platform", "\"Linux\""], ["accept", "image/avif,image/webp,image/apng,image/svg+xml,image/*,*/*;q=0.8"], ["sec-fetch-site", "same-origin"], ["sec-fetch-mode", "no-cors"], ["sec-fetch-dest", "image"], ["referer", "https://thenai.org/"], ["accept-encoding", "gzip, deflate, br"]], [["sec-ch-ua", "\"Not.A/Brand\";v=\"8\", \"Chromium\";v=\"114\", \"HeadlessChrome\";v=\"114\""], ["sec-ch-ua-mobile", "?0"], ["user-agent", "Mozilla/5.0 (X11; Linux x86_64) AppleWebKit/537.36 (KHTML, like Gecko) HeadlessChrome/114.0.5735.90 Safari/537.36"], ["sec-ch-ua-platform", "\"Linux\""], ["accept", "image/avif,image/webp,image/apng,image/svg+xml,image/*,*/*;q=0.8"], ["sec-fetch-site", "same-origin"], ["sec-fetch-mode", "no-cors"], ["sec-fetch-dest", "image"], ["referer", "https://thenai.org/"], ["accept-encoding", "gzip, deflate, br"]], [["sec-ch-ua", "\"Not.A/Brand\";v=\"8\", \"Chromium\";v=\"114\", \"HeadlessChrome\";v=\"114\""], ["sec-ch-ua-mobile", "?0"], ["user-agent", "Mozilla/5.0 (X11; Linux x86_64) AppleWebKit/537.36 (KHTML, like Gecko) HeadlessChrome/114.0.5735.90 Safari/537.36"], ["sec-ch-ua-platform", "\"Linux\""], ["accept", "image/avif,image/webp,image/apng,image/svg+xml,image/*,*/*;q=0.8"], ["sec-fetch-site", "same-origin"], ["sec-fetch-mode", "no-cors"], ["sec-fetch-dest", "image"], ["referer", "https://thenai.org/"], ["accept-encoding", "gzip, deflate, br"]], [["sec-ch-ua", "\"Not.A/Brand\";v=\"8\", \"Chromium\";v=\"114\", \"HeadlessChrome\";v=\"114\""], ["sec-ch-ua-mobile", "?0"], ["user-agent", "Mozilla/5.0 (X11; Linux x86_64) AppleWebKit/537.36 (KHTML, like Gecko) HeadlessChrome/114.0.5735.90 Safari/537.36"], ["sec-ch-ua-platform", "\"Linux\""], ["accept", "image/avif,image/webp,image/apng,image/svg+xml,image/*,*/*;q=0.8"], ["sec-fetch-site", "same-origin"], ["sec-fetch-mode", "no-cors"], ["sec-fetch-dest", "image"], ["referer", "https://thenai.org/"], ["accept-encoding", "gzip, deflate, br"]], [["sec-ch-ua", "\"Not.A/Brand\";v=\"8\", \"Chromium\";v=\"114\", \"HeadlessChrome\";v=\"114\""], ["sec-ch-ua-mobile", "?0"], ["user-agent", "Mozilla/5.0 (X11; Linux x86_64) AppleWebKit/537.36 (KHTML, like Gecko) HeadlessChrome/114.0.5735.90 Safari/537.36"], ["sec-ch-ua-platform", "\"Linux\""], ["accept", "image/avif,image/webp,image/apng,image/svg+xml,image/*,*/*;q=0.8"], ["sec-fetch-site", "same-origin"], ["sec-fetch-mode", "no-cors"], ["sec-fetch-dest", "image"], ["referer", "https://thenai.org/"], ["accept-encoding", "gzip, deflate, br"]], [["sec-ch-ua", "\"Not.A/Brand\";v=\"8\", \"Chromium\";v=\"114\", \"HeadlessChrome\";v=\"114\""], ["sec-ch-ua-mobile", "?0"], ["user-agent", "Mozilla/5.0 (X11; Linux x86_64) AppleWebKit/537.36 (KHTML, like Gecko) HeadlessChrome/114.0.5735.90 Safari/537.36"], ["sec-ch-ua-platform", "\"Linux\""], ["accept", "image/avif,image/webp,image/apng,image/svg+xml,image/*,*/*;q=0.8"], ["sec-fetch-site", "same-origin"], ["sec-fetch-mode", "no-cors"], ["sec-fetch-dest", "image"], ["referer", "https://thenai.org/"], ["accept-encoding", "gzip, deflate, br"]], [["sec-ch-ua", "\"Not.A/Brand\";v=\"8\", \"Chromium\";v=\"114\", \"HeadlessChrome\";v=\"114\""], ["sec-ch-ua-mobile", "?0"], ["user-agent", "Mozilla/5.0 (X11; Linux x86_64) AppleWebKit/537.36 (KHTML, like Gecko) HeadlessChrome/114.0.5735.90 Safari/537.36"], ["sec-ch-ua-platform", "\"Linux\""], ["accept", "image/avif,image/webp,image/apng,image/svg+xml,image/*,*/*;q=0.8"], ["sec-fetch-site", "same-origin"], ["sec-fetch-mode", "no-cors"], ["sec-fetch-dest", "image"], ["referer", "https://thenai.org/"], ["accept-encoding", "gzip, deflate, br"]], [["sec-ch-ua", "\"Not.A/Brand\";v=\"8\", \"Chromium\";v=\"114\", \"HeadlessChrome\";v=\"114\""], ["sec-ch-ua-mobile", "?0"], ["user-agent", "Mozilla/5.0 (X11; Linux x86_64) AppleWebKit/537.36 (KHTML, like Gecko) HeadlessChrome/114.0.5735.90 Safari/537.36"], ["sec-ch-ua-platform", "\"Linux\""], ["accept", "image/avif,image/webp,image/apng,image/svg+xml,image/*,*/*;q=0.8"], ["sec-fetch-site", "same-origin"], ["sec-fetch-mode", "no-cors"], ["sec-fetch-dest", "image"], ["referer", "https://thenai.org/"], ["accept-encoding", "gzip, deflate, br"]], [["sec-ch-ua", "\"Not.A/Brand\";v=\"8\", \"Chromium\";v=\"114\", \"HeadlessChrome\";v=\"114\""], ["sec-ch-ua-mobile", "?0"], ["user-agent", "Mozilla/5.0 (X11; Linux x86_64) AppleWebKit/537.36 (KHTML, like Gecko) HeadlessChrome/114.0.5735.90 Safari/537.36"], ["sec-ch-ua-platform", "\"Linux\""], ["accept", "*/*"], ["sec-fetch-site", "cross-site"], ["sec-fetch-mode", "no-cors"], ["sec-fetch-dest", "script"], ["referer", "https://thenai.org/"], ["accept-encoding", "gzip, deflate, br"]], [["content-length", "0"], ["sec-ch-ua", "\"Not.A/Brand\";v=\"8\", \"Chromium\";v=\"114\", \"HeadlessChrome\";v=\"114\""], ["sec-ch-ua-platform", "\"Linux\""], ["sec-ch-ua-mobile", "?0"], ["user-agent", "Mozilla/5.0 (X11; Linux x86_64) AppleWebKit/537.36 (KHTML, like Gecko) HeadlessChrome/114.0.5735.90 Safari/537.36"], ["content-type", "text/plain"], ["accept", "*/*"], ["origin", "https://thenai.org"], ["sec-fetch-site", "cross-site"], ["sec-fetch-mode", "cors"], ["sec-fetch-dest", "empty"], ["referer", "https://thenai.org/"], ["accept-encoding", "gzip, deflate, br"]]], "response_headers": [[["Content-Length", "0"], ["Connection", "keep-alive"], ["Date", "Sat, 03 Jun 2023 02:50:55 GMT"], ["Location", "https://thenai.org/"], ["Server", "AmazonS3"], ["X-Cache", "Miss from cloudfront"], ["Via", "1.1 9c920cc684a38b53bc9c7a44ba794874.cloudfront.net (CloudFront)"], ["X-Amz-Cf-Pop", "FRA60-P4"], ["X-Amz-Cf-Id", "Hxl3BulVJf6uEeVpPLAcbynpXOsjL8t_Pm3NPd8btM-MKmvCZINDyw=="]], [["date", "Sat, 03 Jun 2023 02:50:56 GMT"], ["content-type", "text/html; charset=UTF-8"], ["vary", "Accept-Encoding"], ["vary", "Accept-Encoding"], ["vary", "Accept-Encoding"], ["vary", "Accept-Encoding"], ["x-powered-by", "WP Engine"], ["link", "<https://thenai.org/wp-json/>; rel=\"https://api.w.org/\""], ["link", "<https://thenai.org/wp-json/>; rel=\"https://api.w.org/\""], ["link", "<https://thenai.org/wp-json/>; rel=\"https://api.w.org/\""], ["x-tec-api-version", "v1"], ["x-tec-api-root", "https://thenai.org/wp-json/tribe/events/v1/"], ["x-tec-api-origin", "https://thenai.org"], ["x-cacheable", "SHORT"], ["cache-control", "max-age=600, must-revalidate"], ["x-cache", "HIT: 71"], ["x-cache-group", "normal"], ["cf-cache-status", "DYNAMIC"], ["report-to", "{\"endpoints\":[{\"url\":\"https:\\/\\/a.nel.cloudflare.com\\/report\\/v3?s=QPs6prnCXXjFovYkhIV3nz8hjRw82B426xLodiHw0UHYIWKIwEKu4qknbZjj04rNTHtPxb9vUqvhBU%2Fr5yPhYA3%2FLUpr3YgWi8N0hgb3ILj%2F6RyW1NGt%2BuEsrVs%3D\"}],\"group\":\"cf-nel\",\"max_age\":604800}"], ["nel", "{\"success_fraction\":0,\"report_to\":\"cf-nel\",\"max_age\":604800}"], ["server", "cloudflare"], ["cf-ray", "7d14a1a5ba3c779b-LHR"], ["content-encoding", "br"], ["alt-svc", "h3=\":443\"; ma=86400"]], [["date", "Sat, 03 Jun 2023 02:50:57 GMT"], ["content-type", "text/css"], ["vary", "Accept-Encoding"], ["vary", "Accept-Encoding"], ["last-modified", "Tue, 25 Oct 2022 13:45:16 GMT"], ["etag", "W/\"6357e86c-d9\""], ["cache-control", "public, max-age=31536000"], ["access-control-allow-origin", "*"], ["cf-cache-status", "HIT"], ["age", "968731"], ["report-to", "{\"endpoints\":[{\"url\":\"https:\\/\\/a.nel.cloudflare.com\\/report\\/v3?s=KFSeojnDROUpesxR%2B7WycwXjTjLPyDNRT0nTSf5lWlZvbwt2PcHUCsphLNLfFkfZQGe9LQtv8eEEHRHntrzr73y2bTark5%2BkAFKECH58EzkUc87zdrlPs4J9NUY%3D\"}],\"group\":\"cf-nel\",\"max_age\":604800}"], ["nel", "{\"success_fraction\":0,\"report_to\":\"cf-nel\",\"max_age\":604800}"], ["server", "cloudflare"], ["cf-ray", "7d14a1ad9e02779b-LHR"], ["content-encoding", "br"], ["alt-svc", "h3=\":443\"; ma=86400"]], [["date", "Sat, 03 Jun 2023 02:50:57 GMT"], ["content-type", "text/css"], ["vary", "Accept-Encoding"], ["vary", "Accept-Encoding"], ["vary", "Accept-Encoding"], ["vary", "Accept-Encoding"], ["last-modified", "Thu, 30 Mar 2023 01:23:35 GMT"], ["etag", "W/\"6424e497-5ef\""], ["cache-control", "public, max-age=31536000"], ["access-control-allow-origin", "*"], ["cf-cache-status", "HIT"], ["age", "1914676"], ["report-to", "{\"endpoints\":[{\"url\":\"https:\\/\\/a.nel.cloudflare.com\\/report\\/v3?s=%2FDBTkVTRdfFO4%2FFvMFQx%2FilTowXZ4EmSpZ1uLYvUG4%2FernAd6DjIhPZcp6v5MQFTr4wNf4l8AEWSghCYMTjyTCVi%2BWLn%2Fr0aqzFC6twsvbCHEd8%2BPPg4vYc51jI%3D\"}],\"group\":\"cf-nel\",\"max_age\":604800}"], ["nel", "{\"success_fraction\":0,\"report_to\":\"cf-nel\",\"max_age\":604800}"], ["server", "cloudflare"], ["cf-ray", "7d14a1aefeb8779b-LHR"], ["content-encoding", "br"], ["alt-svc", "h3=\":443\"; ma=86400"]], [["date", "Sat, 03 Jun 2023 02:50:57 GMT"], ["content-type", "text/css"], ["vary", "Accept-Encoding"], ["vary", "Accept-Encoding"], ["vary", "Accept-Encoding"], ["last-modified", "Mon, 04 Jul 2022 12:10:37 GMT"], ["etag", "W/\"62c2d8bd-15b64\""], ["cache-control", "public, max-age=31536000"], ["access-control-allow-origin", "*"], ["cf-cache-status", "HIT"], ["age", "19854918"], ["report-to", "{\"endpoints\":[{\"url\":\"https:\\/\\/a.nel.cloudflare.com\\/report\\/v3?s=odYyQe7lQSCj729zP0NjG8WB%2BWow7PxDL48vyl%2BkXkLqzKIccfCKqqvI3TFRe1a54x%2FYcPJxLVyZOxLiiRd0PIgQDp0JqJ%2Fgazs2WhOST7Bsiy8c8GcQ3Lwsea8%3D\"}],\"group\":\"cf-nel\",\"max_age\":604800}"], ["nel", "{\"success_fraction\":0,\"report_to\":\"cf-nel\",\"max_age\":604800}"], ["server", "cloudflare"], ["cf-ray", "7d14a1af2eca779b-LHR"], ["content-encoding", "br"], ["alt-svc", "h3=\":443\"; ma=86400"]], [["date", "Sat, 03 Jun 2023 02:50:57 GMT"], ["content-type", "text/css"], ["vary", "Accept-Encoding"], ["vary", "Accept-Encoding"], ["vary", "Accept-Encoding"], ["vary", "Accept-Encoding"], ["last-modified", "Sat, 29 Jan 2022 19:20:20 GMT"], ["etag", "W/\"61f59374-183c0\""], ["cache-control", "public, max-age=31536000"], ["access-control-allow-origin", "*"], ["cf-cache-status", "HIT"], ["age", "11078049"], ["report-to", "{\"endpoints\":[{\"url\":\"https:\\/\\/a.nel.cloudflare.com\\/report\\/v3?s=RsDcq5YMXw5%2Fp%2Bb4%2BaBkp7XHXRKD99ZAFISd12PLElO9pyHI23I86dfCqmHz16DZ8%2FeqLmjzX5yJavFNf16I8j9GG3LiRgu5WP44%2F5iS%2FRbre53xfRNYtYj8q1k%3D\"}],\"group\":\"cf-nel\",\"max_age\":604800}"], ["nel", "{\"success_fraction\":0,\"report_to\":\"cf-nel\",\"max_age\":604800}"], ["server", "cloudflare"], ["cf-ray", "7d14a1af2ecb779b-LHR"], ["content-encoding", "br"], ["alt-svc", "h3=\":443\"; ma=86400"]], [["date", "Sat, 03 Jun 2023 02:50:57 GMT"], ["content-type", "application/javascript"], ["vary", "Accept-Encoding"], ["vary", "Accept-Encoding"], ["vary", "Accept-Encoding"], ["vary", "Accept-Encoding"], ["last-modified", "Mon, 19 Sep 2022 14:16:24 GMT"], ["etag", "W/\"632879b8-15e54\""], ["cache-control", "public, max-age=31536000"], ["access-control-allow-origin", "*"], ["cf-cache-status", "HIT"], ["age", "15247308"], ["report-to", "{\"endpoints\":[{\"url\":\"https:\\/\\/a.nel.cloudflare.com\\/report\\/v3?s=PjAz9osCLrIp0fG6A7SmIuQnp%2Btyi%2FMtz5m6bGjgxGcCUw6im%2BihSvLgqfTRGiGvdudPcXuNWNqVn%2BPNPC1bNYizkth2dk1pOymwQp2fdkyLIm71y8sY78OoJlE%3D\"}],\"group\":\"cf-nel\",\"max_age\":604800}"], ["nel", "{\"success_fraction\":0,\"report_to\":\"cf-nel\",\"max_age\":604800}"], ["server", "cloudflare"], ["cf-ray", "7d14a1af2ecc779b-LHR"], ["content-encoding", "br"], ["alt-svc", "h3=\":443\"; ma=86400"]], [["date", "Sat, 03 Jun 2023 02:50:57 GMT"], ["content-type", "application/javascript"], ["vary", "Accept-Encoding"], ["vary", "Accept-Encoding"], ["vary", "Accept-Encoding"], ["vary", "Accept-Encoding"], ["last-modified", "Wed, 18 Nov 2020 09:06:06 GMT"], ["etag", "W/\"5fb4e3fe-2bd8\""], ["cache-control", "public, max-age=31536000"], ["access-control-allow-origin", "*"], ["cf-cache-status", "HIT"], ["age", "10286885"], ["report-to", "{\"endpoints\":[{\"url\":\"https:\\/\\/a.nel.cloudflare.com\\/report\\/v3?s=eLXowM7HsuUKP2UW5BFzVh5Bbpgg6LGlkIg1Ydpry3iOYyJwf%2BH5qNA54DF%2FPai%2B2Mxt4xjyonnAyLqWyjyUWW0yYei7IPqOFT9iGf7W14N3bqZ6MApfOOM%2F2fw%3D\"}],\"group\":\"cf-nel\",\"max_age\":604800}"], ["nel", "{\"success_fraction\":0,\"report_to\":\"cf-nel\",\"max_age\":604800}"], ["server", "cloudflare"], ["cf-ray", "7d14a1afcf0a779b-LHR"], ["content-encoding", "br"], ["alt-svc", "h3=\":443\"; ma=86400"]], [["server", "nginx"], ["content-type", "text/css;charset=utf-8"], ["vary", "Accept-Encoding"], ["strict-transport-security", "max-age=31536000; includeSubDomains;"], ["cache-control", "private, max-age=600, stale-while-revalidate=604800"], ["timing-allow-origin", "*"], ["access-control-allow-origin", "*"], ["cross-origin-resource-policy", "cross-origin"], ["content-encoding", "gzip"], ["content-length", "771"], ["date", "Sat, 03 Jun 2023 02:50:58 GMT"]], [["date", "Sat, 03 Jun 2023 02:50:58 GMT"], ["content-type", "application/javascript"], ["vary", "Accept-Encoding"], ["vary", "Accept-Encoding"], ["vary", "Accept-Encoding"], ["last-modified", "Sat, 29 Jan 2022 19:20:20 GMT"], ["etag", "W/\"61f59374-7498c\""], ["cache-control", "public, max-age=31536000"], ["access-control-allow-origin", "*"], ["cf-cache-status", "HIT"], ["age", "19854919"], ["report-to", "{\"endpoints\":[{\"url\":\"https:\\/\\/a.nel.cloudflare.com\\/report\\/v3?s=pyrs4MzP2EeRMyb%2BV1anx5WpEkO3tbIF9cbOKsg%2F9bQhGOpLg6qyJjweFpMrLppc8NH2ZjRYDhg1VeLtgexHglaLpxzbzgMeRR8i7b0OwQWqxRA7HRhjZ2UmBCE%3D\"}],\"group\":\"cf-nel\",\"max_age\":604800}"], ["nel", "{\"success_fraction\":0,\"report_to\":\"cf-nel\",\"max_age\":604800}"], ["server", "cloudflare"], ["cf-ray", "7d14a1b358b6779b-LHR"], ["content-encoding", "br"], ["alt-svc", "h3=\":443\"; ma=86400"]], [["date", "Sat, 03 Jun 2023 02:50:59 GMT"], ["content-type", "application/javascript"], ["vary", "Accept-Encoding"], ["vary", "Accept-Encoding"], ["vary", "Accept-Encoding"], ["last-modified", "Sat, 29 Jan 2022 19:20:20 GMT"], ["etag", "W/\"61f59374-2e12\""], ["cache-control", "public, max-age=31536000"], ["access-control-allow-origin", "*"], ["cf-cache-status", "HIT"], ["age", "19854920"], ["report-to", "{\"endpoints\":[{\"url\":\"https:\\/\\/a.nel.cloudflare.com\\/report\\/v3?s=GNiCKvqNaCoNzGo2vmRzvoZfKCKtJ%2FrVOIEUHTNkrJRQxovize7jxVq3aSSi25nGjXAMEyuyWT4rbgStMTsisRcQE2oHBVXY2YWhpVfkrUS3tMCYOQSLU0VLdVM%3D\"}],\"group\":\"cf-nel\",\"max_age\":604800}"], ["nel", "{\"success_fraction\":0,\"report_to\":\"cf-nel\",\"max_age\":604800}"], ["server", "cloudflare"], ["cf-ray", "7d14a1b7daae779b-LHR"], ["content-encoding", "br"], ["alt-svc", "h3=\":443\"; ma=86400"]], [["server", "nginx"], ["content-type", "text/css"], ["content-length", "5"], ["last-modified", "Fri, 21 Apr 2023 14:00:42 GMT"], ["etag", "\"6442970a-5\""], ["cache-control", "public, max-age=604800"], ["access-control-allow-origin", "*"], ["cross-origin-resource-policy", "cross-origin"], ["accept-ranges", "bytes"], ["date", "Sat, 03 Jun 2023 02:51:00 GMT"]], [["date", "Sat, 03 Jun 2023 02:51:00 GMT"], ["content-type", "application/javascript"], ["vary", "Accept-Encoding"], ["vary", "Accept-Encoding"], ["last-modified", "Wed, 27 Jul 2022 04:20:10 GMT"], ["etag", "W/\"62e0bcfa-81\""], ["cache-control", "public, max-age=31536000"], ["access-control-allow-origin", "*"], ["cf-cache-status", "HIT"], ["age", "19854921"], ["report-to", "{\"endpoints\":[{\"url\":\"https:\\/\\/a.nel.cloudflare.com\\/report\\/v3?s=ZMJOk%2BU1xsCiPZVrBC77Nn%2FfyzmHHHWK%2BsXV3%2Fy5n%2BuoGTGBwGctUgNLnFYR%2FGpC4zy4w0Ijhjd%2Fg1AtM7mi1uOHGjGJN%2FDFB8mQi8JhZA5nkPqolXuNePjvOd0%3D\"}],\"group\":\"cf-nel\",\"max_age\":604800}"], ["nel", "{\"success_fraction\":0,\"report_to\":\"cf-nel\",\"max_age\":604800}"], ["server", "cloudflare"], ["cf-ray", "7d14a1c25f92779b-LHR"], ["content-encoding", "br"], ["alt-svc", "h3=\":443\"; ma=86400"]], [["date", "Sat, 03 Jun 2023 02:51:01 GMT"], ["content-type", "image/webp"], ["content-length", "5646"], ["access-control-allow-origin", "*"], ["cache-control", "public, max-age=31536000"], ["cf-bgj", "imgq:100,h2pri"], ["cf-polished", "origFmt=png, origSize=10123"], ["content-disposition", "inline; filename=\"NAI_logo.webp\""], ["etag", "\"61bc00c1-278b\""], ["last-modified", "Fri, 17 Dec 2021 03:15:13 GMT"], ["vary", "Accept"], ["cf-cache-status", "HIT"], ["age", "278323"], ["accept-ranges", "bytes"], ["report-to", "{\"endpoints\":[{\"url\":\"https:\\/\\/a.nel.cloudflare.com\\/report\\/v3?s=4mrRPb%2BeQAy4aNLlDeSWh%2Fjpf4mCnezYDqhCRnfz34ryLGpqUK%2FpF153XMSGtjyGqaJ4XfO%2BOvvDUrs0ew4EIsoJYGJaR5ZoF826SDZ%2F1wVN6P%2BphjmnITmXO5M%3D\"}],\"group\":\"cf-nel\",\"max_age\":604800}"], ["nel", "{\"success_fraction\":0,\"report_to\":\"cf-nel\",\"max_age\":604800}"], ["server", "cloudflare"], ["cf-ray", "7d14a1c4283e779b-LHR"], ["alt-svc", "h3=\":443\"; ma=86400"]], [["date", "Sat, 03 Jun 2023 02:51:01 GMT"], ["content-type", "image/jpeg"], ["content-length", "151185"], ["access-control-allow-origin", "*"], ["cache-control", "public, max-age=31536000"], ["cf-bgj", "imgq:100,h2pri"], ["cf-polished", "origSize=174214, status=webp_bigger"], ["etag", "\"61bc00c1-2a886\""], ["last-modified", "Fri, 17 Dec 2021 03:15:13 GMT"], ["vary", "Accept-Encoding"], ["cf-cache-status", "HIT"], ["age", "19854922"], ["accept-ranges", "bytes"], ["report-to", "{\"endpoints\":[{\"url\":\"https:\\/\\/a.nel.cloudflare.com\\/report\\/v3?s=Pi4G8uVZSO9na7NCvj8y%2Bx35haTtganA5iND6NuPBPvNHH2ytha1hBMsrBgAKTwHwiM1%2FjkWvmMBDFmDIEfxwF%2BaK45gtDQzsURrpuBPJHKHEkCK1T2qHzvlx0Q%3D\"}],\"group\":\"cf-nel\",\"max_age\":604800}"], ["nel", "{\"success_fraction\":0,\"report_to\":\"cf-nel\",\"max_age\":604800}"], ["server", "cloudflare"], ["cf-ray", "7d14a1c4b880779b-LHR"], ["alt-svc", "h3=\":443\"; ma=86400"]], [["date", "Sat, 03 Jun 2023 02:51:01 GMT"], ["content-type", "image/webp"], ["content-length", "104502"], ["access-control-allow-origin", "*"], ["cache-control", "public, max-age=31536000"], ["cf-bgj", "imgq:100,h2pri"], ["cf-polished", "origFmt=jpeg, origSize=253284"], ["content-disposition", "inline; filename=\"nav_image_2.webp\""], ["etag", "\"61bc00c1-3dd64\""], ["last-modified", "Fri, 17 Dec 2021 03:15:13 GMT"], ["vary", "Accept"], ["cf-cache-status", "HIT"], ["age", "1482878"], ["accept-ranges", "bytes"], ["report-to", "{\"endpoints\":[{\"url\":\"https:\\/\\/a.nel.cloudflare.com\\/report\\/v3?s=DO95cg%2Bd0hK9oWDREHgAyXJMr7gG6K%2F2hYd0LQ%2Bk3nwcH6EUkn5prHo9V2KzVHr4EXYpBDMU08Me%2FMKO5y21HqsKVtl1oTNWTK0Y4dlLy9Xr7Kefy73ceOzT8Gw%3D\"}],\"group\":\"cf-nel\",\"max_age\":604800}"], ["nel", "{\"success_fraction\":0,\"report_to\":\"cf-nel\",\"max_age\":604800}"], ["server", "cloudflare"], ["cf-ray", "7d14a1c5089b779b-LHR"], ["alt-svc", "h3=\":443\"; ma=86400"]], [["date", "Sat, 03 Jun 2023 02:51:01 GMT"], ["content-type", "application/javascript; charset=utf-8"], ["cache-control", "public, max-age=172800"], ["cf-bgj", "minify"], ["access-control-allow-origin", "*"], ["age", "155433"], ["etag", "W/\"c09-5fd0c830881f6\""], ["last-modified", "Thu, 01 Jun 2023 07:37:43 GMT"], ["vary", "Accept-Encoding"], ["via", "e4s"], ["x-content-type-options", "nosniff"], ["cf-cache-status", "HIT"], ["strict-transport-security", "max-age=31536000; includeSubDomains; preload"], ["server", "cloudflare"], ["cf-ray", "7d14a1c55a1424da-LHR"], ["content-encoding", "br"], ["alt-svc", "h3=\":443\"; ma=86400"]], [["date", "Sat, 03 Jun 2023 02:51:01 GMT"], ["content-type", "image/jpeg"], ["content-length", "308273"], ["access-control-allow-origin", "*"], ["cache-control", "public, max-age=31536000"], ["cf-bgj", "imgq:100,h2pri"], ["cf-polished", "origSize=333401, status=webp_bigger"], ["etag", "\"61bc00c1-51659\""], ["last-modified", "Fri, 17 Dec 2021 03:15:13 GMT"], ["vary", "Accept-Encoding"], ["cf-cache-status", "HIT"], ["age", "19854922"], ["accept-ranges", "bytes"], ["report-to", "{\"endpoints\":[{\"url\":\"https:\\/\\/a.nel.cloudflare.com\\/report\\/v3?s=xUk6wGEBd18lT%2FAZgvf%2FPvcKn75aV4AyGwtV9ew9zA5ekup0%2FZkVrAKat0LxpSwK6w51ENBjKpGOKT1bIf5ryUv0BJq%2B0xyXJTc%2Fd1TH943%2BaxyP6lgNTS2E0r4%3D\"}],\"group\":\"cf-nel\",\"max_age\":604800}"], ["nel", "{\"success_fraction\":0,\"report_to\":\"cf-nel\",\"max_age\":604800}"], ["server", "cloudflare"], ["cf-ray", "7d14a1c91aa3779b-LHR"], ["alt-svc", "h3=\":443\"; ma=86400"]], [["date", "Sat, 03 Jun 2023 02:51:01 GMT"], ["content-type", "image/jpeg"], ["content-length", "73739"], ["access-control-allow-origin", "*"], ["cache-control", "public, max-age=31536000"], ["cf-bgj", "imgq:100,h2pri"], ["cf-polished", "origSize=94565, status=webp_bigger"], ["etag", "\"61bc00c1-17165\""], ["last-modified", "Fri, 17 Dec 2021 03:15:13 GMT"], ["vary", "Accept-Encoding"], ["cf-cache-status", "HIT"], ["age", "19854972"], ["accept-ranges", "bytes"], ["report-to", "{\"endpoints\":[{\"url\":\"https:\\/\\/a.nel.cloudflare.com\\/report\\/v3?s=nmcALkM65SaBSL6jQ8m1%2Fzk9oEvirHwK6Fn3ueDaGvCX%2BjFjhHNn3U2bSOqDaibGdF4LGUP2ge6kh1LyQ68JzSX1tokkOkq3vw2BEzUbbub41mE2B9wfOv2fuBQ%3D\"}],\"group\":\"cf-nel\",\"max_age\":604800}"], ["nel", "{\"success_fraction\":0,\"report_to\":\"cf-nel\",\"max_age\":604800}"], ["server", "cloudflare"], ["cf-ray", "7d14a1c96ad0779b-LHR"], ["alt-svc", "h3=\":443\"; ma=86400"]], [["date", "Sat, 03 Jun 2023 02:51:02 GMT"], ["content-type", "image/webp"], ["content-length", "2437964"], ["access-control-allow-origin", "*"], ["cache-control", "public, max-age=31536000"], ["cf-bgj", "imgq:100,h2pri"], ["cf-polished", "origFmt=png, origSize=3703371"], ["content-disposition", "inline; filename=\"Untitled-design-10.webp\""], ["etag", "\"62b30fbb-38824b\""], ["last-modified", "Wed, 22 Jun 2022 12:48:59 GMT"], ["vary", "Accept"], ["cf-cache-status", "HIT"], ["age", "2540313"], ["accept-ranges", "bytes"], ["report-to", "{\"endpoints\":[{\"url\":\"https:\\/\\/a.nel.cloudflare.com\\/report\\/v3?s=gxLOxmjbYy0WKX%2BebTPQb9sJva%2FvvhAsai%2BlbfE2uCvdAHe7T4qRCOyFkJT6Tv4Pw52p67m%2Bwfk1oj2morKUMY76nqZhchFI0YdD8WYvfy7cl0F1Dq9N5UozDFQ%3D\"}],\"group\":\"cf-nel\",\"max_age\":604800}"], ["nel", "{\"success_fraction\":0,\"report_to\":\"cf-nel\",\"max_age\":604800}"], ["server", "cloudflare"], ["cf-ray", "7d14a1cc4c02779b-LHR"], ["alt-svc", "h3=\":443\"; ma=86400"]], [["date", "Sat, 03 Jun 2023 02:51:02 GMT"], ["content-type", "image/jpeg"], ["content-length", "213642"], ["access-control-allow-origin", "*"], ["cache-control", "public, max-age=31536000"], ["cf-bgj", "imgq:100,h2pri"], ["cf-polished", "origSize=237245, status=webp_bigger"], ["etag", "\"61bc00c1-39ebd\""], ["last-modified", "Fri, 17 Dec 2021 03:15:13 GMT"], ["vary", "Accept-Encoding"], ["cf-cache-status", "HIT"], ["age", "12820988"], ["accept-ranges", "bytes"], ["report-to", "{\"endpoints\":[{\"url\":\"https:\\/\\/a.nel.cloudflare.com\\/report\\/v3?s=fRjyaEhQP%2B7rV6ikH%2FICC8o6fVqe7Mh5yTbD4%2BfSToCHNnrB2kogPxmiv07%2FJimXb4h%2BsatBcVo826%2FgxLxZyoPrWuk7s9eJBbi04rYau3bH0vLF44WE%2FDbyMgs%3D\"}],\"group\":\"cf-nel\",\"max_age\":604800}"], ["nel", "{\"success_fraction\":0,\"report_to\":\"cf-nel\",\"max_age\":604800}"], ["server", "cloudflare"], ["cf-ray", "7d14a1cbebd9779b-LHR"], ["alt-svc", "h3=\":443\"; ma=86400"]], [["date", "Sat, 03 Jun 2023 02:51:02 GMT"], ["content-type", "image/png"], ["content-length", "1230667"], ["access-control-allow-origin", "*"], ["cache-control", "public, max-age=31536000"], ["cf-bgj", "imgq:100,h2pri"], ["cf-polished", "origSize=2466636, status=webp_bigger"], ["etag", "\"61bc00c0-25a34c\""], ["last-modified", "Fri, 17 Dec 2021 03:15:12 GMT"], ["vary", "Accept-Encoding"], ["cf-cache-status", "HIT"], ["age", "19853807"], ["accept-ranges", "bytes"], ["report-to", "{\"endpoints\":[{\"url\":\"https:\\/\\/a.nel.cloudflare.com\\/report\\/v3?s=AQCldkqoLTAanHr37AG68Efar%2B3ChqQ2XVt0J6WNEFPyHTSnF7Las1whP%2FJ3CQ1E7BYxjRDkkABTveTWNyIR2GBoxznI4Rk8RxRwTggQlAFbBrIHzljTpkMq5%2FA%3D\"}],\"group\":\"cf-nel\",\"max_age\":604800}"], ["nel", "{\"success_fraction\":0,\"report_to\":\"cf-nel\",\"max_age\":604800}"], ["server", "cloudflare"], ["cf-ray", "7d14a1ce5dcf779b-LHR"], ["alt-svc", "h3=\":443\"; ma=86400"]], [["content-type", "application/javascript; charset=UTF-8"], ["access-control-allow-origin", "*"], ["access-control-allow-credentials", "true"], ["access-control-allow-headers", "Cache-Control"], ["content-encoding", "br"], ["vary", "Accept-Encoding"], ["date", "Sat, 03 Jun 2023 02:51:02 GMT"], ["expires", "Sat, 03 Jun 2023 02:51:02 GMT"], ["cache-control", "private, max-age=900"], ["last-modified", "Sat, 03 Jun 2023 00:05:39 GMT"], ["strict-transport-security", "max-age=31536000; includeSubDomains"], ["cross-origin-resource-policy", "cross-origin"], ["server", "Google Tag Manager"], ["content-length", "47372"], ["x-xss-protection", "0"], ["alt-svc", "h3=\":443\"; ma=2592000,h3-29=\":443\"; ma=2592000"]], [["date", "Sat, 03 Jun 2023 02:51:03 GMT"], ["content-type", "image/webp"], ["content-length", "98876"], ["access-control-allow-origin", "*"], ["cache-control", "public, max-age=31536000"], ["cf-bgj", "imgq:100,h2pri"], ["cf-polished", "origFmt=png, origSize=187536"], ["content-disposition", "inline; filename=\"NAI_OpenGraph_Final.webp\""], ["etag", "\"61bc00c1-2dc90\""], ["last-modified", "Fri, 17 Dec 2021 03:15:13 GMT"], ["vary", "Accept"], ["cf-cache-status", "HIT"], ["age", "2539148"], ["accept-ranges", "bytes"], ["report-to", "{\"endpoints\":[{\"url\":\"https:\\/\\/a.nel.cloudflare.com\\/report\\/v3?s=zrRMX%2FPceDR8s64CazzTEjqwSFgmprS%2BrTWvO7jFHb2pDCib%2FQ7aFk4uhvTS9NWFjIm9QvJ7R6Z0dUjPzuitJPmuLJg2U8BjqHceVMva849dTelgzEF%2FL%2BKIcSE%3D\"}],\"group\":\"cf-nel\",\"max_age\":604800}"], ["nel", "{\"success_fraction\":0,\"report_to\":\"cf-nel\",\"max_age\":604800}"], ["server", "cloudflare"], ["cf-ray", "7d14a1d188d4779b-LHR"], ["alt-svc", "h3=\":443\"; ma=86400"]], [["date", "Sat, 03 Jun 2023 02:51:03 GMT"], ["content-type", "image/jpeg"], ["content-length", "21021"], ["access-control-allow-origin", "*"], ["cache-control", "public, max-age=31536000"], ["cf-bgj", "imgq:100,h2pri"], ["cf-polished", "origSize=33858, status=webp_bigger"], ["etag", "\"641ca810-8442\""], ["last-modified", "Thu, 23 Mar 2023 19:27:12 GMT"], ["vary", "Accept-Encoding"], ["cf-cache-status", "HIT"], ["age", "6157222"], ["accept-ranges", "bytes"], ["report-to", "{\"endpoints\":[{\"url\":\"https:\\/\\/a.nel.cloudflare.com\\/report\\/v3?s=JIyRcRYMVf7qz4uwgWqQ6cd782ffgh%2Bz9hW6mnwGKHTgevOgDMK3szVQ5g6JvnneEGcWoH%2Fb7trJqUh0uDJVpCOgaOJtGZJEkpvyZHuWctglgLsTq0XGAqrmVoQ%3D\"}],\"group\":\"cf-nel\",\"max_age\":604800}"], ["nel", "{\"success_fraction\":0,\"report_to\":\"cf-nel\",\"max_age\":604800}"], ["server", "cloudflare"], ["cf-ray", "7d14a1d42b28779b-LHR"], ["alt-svc", "h3=\":443\"; ma=86400"]], [["date", "Sat, 03 Jun 2023 02:51:04 GMT"], ["content-type", "image/jpeg"], ["content-length", "878117"], ["access-control-allow-origin", "*"], ["cache-control", "public, max-age=31536000"], ["cf-bgj", "imgq:100,h2pri"], ["cf-polished", "origSize=919142"], ["etag", "\"64760181-e0666\""], ["last-modified", "Tue, 30 May 2023 14:00:33 GMT"], ["vary", "Accept-Encoding"], ["cf-cache-status", "HIT"], ["age", "304697"], ["accept-ranges", "bytes"], ["report-to", "{\"endpoints\":[{\"url\":\"https:\\/\\/a.nel.cloudflare.com\\/report\\/v3?s=Qiy%2FPr85pdniijFSirq351%2FZBhzp7M7nrzdKSvcppYnmE7SpX9TqJzY6iLoR9PhXA2RRaL8RXcZaqdk%2BG%2BMF5PTiFWw0avaj7K26TGCzRbBzzaAXaKz6WGRWhQo%3D\"}],\"group\":\"cf-nel\",\"max_age\":604800}"], ["nel", "{\"success_fraction\":0,\"report_to\":\"cf-nel\",\"max_age\":604800}"], ["server", "cloudflare"], ["cf-ray", "7d14a1d7ef26779b-LHR"], ["alt-svc", "h3=\":443\"; ma=86400"]], [["date", "Sat, 03 Jun 2023 02:51:04 GMT"], ["content-type", "image/webp"], ["content-length", "4780"], ["access-control-allow-origin", "*"], ["cache-control", "public, max-age=31536000"], ["cf-bgj", "imgq:100,h2pri"], ["cf-polished", "origFmt=png, origSize=8158"], ["content-disposition", "inline; filename=\"nai_square-e1631130910890.webp\""], ["etag", "\"61bc00c1-1fde\""], ["last-modified", "Fri, 17 Dec 2021 03:15:13 GMT"], ["vary", "Accept"], ["cf-cache-status", "HIT"], ["age", "971622"], ["accept-ranges", "bytes"], ["report-to", "{\"endpoints\":[{\"url\":\"https:\\/\\/a.nel.cloudflare.com\\/report\\/v3?s=CNLuV0sfGbFRuzXyQFFdezATqwYCVGthQslFK6EZWrrmGczdOUUNcm6EytO3n6iH%2Bn%2BMJhPiuwArmW8qQmtynckRm66Txl2BpV0QItY8O0g8G0zXT2trytRYlN0%3D\"}],\"group\":\"cf-nel\",\"max_age\":604800}"], ["nel", "{\"success_fraction\":0,\"report_to\":\"cf-nel\",\"max_age\":604800}"], ["server", "cloudflare"], ["cf-ray", "7d14a1d83f59779b-LHR"], ["alt-svc", "h3=\":443\"; ma=86400"]], [["date", "Sat, 03 Jun 2023 02:51:05 GMT"], ["content-type", "application/octet-stream"], ["content-length", "118544"], ["last-modified", "Sat, 29 Jan 2022 19:20:20 GMT"], ["etag", "\"61f59374-1cf10\""], ["cache-control", "public, max-age=31536000"], ["vary", "Accept-Encoding"], ["access-control-allow-origin", "*"], ["cf-cache-status", "HIT"], ["age", "19854924"], ["accept-ranges", "bytes"], ["report-to", "{\"endpoints\":[{\"url\":\"https:\\/\\/a.nel.cloudflare.com\\/report\\/v3?s=9%2FtPuJbzS%2BW%2BAxCMB210GfvB0eVwrE%2B1dHcdEajPxq4tFNwPLTcvBaiSiE0HxHnYpgXSfEDFJoptklNYc3r9giRK5heR%2FkjjVeMgDbKYdW32%2BFyH9EE%2BqFRN4cI%3D\"}],\"group\":\"cf-nel\",\"max_age\":604800}"], ["nel", "{\"success_fraction\":0,\"report_to\":\"cf-nel\",\"max_age\":604800}"], ["server", "cloudflare"], ["cf-ray", "7d14a1dddcce779b-LHR"], ["alt-svc", "h3=\":443\"; ma=86400"]], [["date", "Sat, 03 Jun 2023 02:51:05 GMT"], ["content-type", "text/html; charset=utf-8"], ["last-modified", "Fri, 18 Nov 2022 00:47:55 GMT"], ["etag", "W/\"2a5-5edb40e6d10d8\""], ["cache-control", "max-age=315360000, immutable"], ["vary", "Accept-Encoding"], ["via", "e4s"], ["cf-cache-status", "HIT"], ["age", "202889"], ["strict-transport-security", "max-age=31536000; includeSubDomains; preload"], ["x-content-type-options", "nosniff"], ["server", "cloudflare"], ["cf-ray", "7d14a1df58b424da-LHR"], ["content-encoding", "br"], ["alt-svc", "h3=\":443\"; ma=86400"]], [["date", "Sat, 03 Jun 2023 02:51:05 GMT"], ["content-type", "image/webp"], ["content-length", "43250"], ["access-control-allow-origin", "*"], ["cache-control", "public, max-age=31536000"], ["cf-bgj", "imgq:100,h2pri"], ["cf-polished", "origFmt=jpeg, origSize=117160"], ["content-disposition", "inline; filename=\"Iowa-Digital.webp\""], ["etag", "\"6425a8a2-1c9a8\""], ["last-modified", "Thu, 30 Mar 2023 15:20:02 GMT"], ["vary", "Accept"], ["cf-cache-status", "HIT"], ["age", "2162944"], ["accept-ranges", "bytes"], ["report-to", "{\"endpoints\":[{\"url\":\"https:\\/\\/a.nel.cloudflare.com\\/report\\/v3?s=l9eqkX0825mpBWxxgTpSSuX0PtqaqvB2GaUNONNdBvLATCkQDIxpHkPVAl6IhRG4%2FwOmcT%2Bf83PPylbBbrK4grDm9zas%2BZnTTo5q7OwaXSMPesUgFy0p7nq%2Bua4%3D\"}],\"group\":\"cf-nel\",\"max_age\":604800}"], ["nel", "{\"success_fraction\":0,\"report_to\":\"cf-nel\",\"max_age\":604800}"], ["server", "cloudflare"], ["cf-ray", "7d14a1e1ff63779b-LHR"], ["alt-svc", "h3=\":443\"; ma=86400"]], [["date", "Sat, 03 Jun 2023 02:51:06 GMT"], ["content-type", "application/javascript; charset=utf-8"], ["cache-control", "max-age=315360000, immutable"], ["cf-bgj", "minify"], ["access-control-allow-origin", "*"], ["etag", "W/\"11397-5fd0c82fc6c36\""], ["last-modified", "Thu, 01 Jun 2023 07:37:42 GMT"], ["vary", "Accept-Encoding"], ["via", "e2s"], ["x-content-type-options", "nosniff"], ["cf-cache-status", "HIT"], ["age", "152003"], ["strict-transport-security", "max-age=31536000; includeSubDomains; preload"], ["server", "cloudflare"], ["cf-ray", "7d14a1e71c399bd0-FRA"], ["content-encoding", "br"], ["alt-svc", "h3=\":443\"; ma=86400"]], [["date", "Sat, 03 Jun 2023 02:51:13 GMT"], ["content-type", "image/webp"], ["content-length", "90942"], ["access-control-allow-origin", "*"], ["cache-control", "public, max-age=31536000"], ["cf-bgj", "imgq:100,h2pri"], ["cf-polished", "origFmt=png, origSize=182885"], ["content-disposition", "inline; filename=\"Joshua-Koran-Blog-Graphic.webp\""], ["etag", "\"64401625-2ca65\""], ["last-modified", "Wed, 19 Apr 2023 16:26:13 GMT"], ["vary", "Accept"], ["cf-cache-status", "HIT"], ["age", "971631"], ["accept-ranges", "bytes"], ["report-to", "{\"endpoints\":[{\"url\":\"https:\\/\\/a.nel.cloudflare.com\\/report\\/v3?s=QypvUichN1FjBVEwUAIxXcaenmBTvagOTQg%2Bdtoq2U8w3rk5fTiQevu16q7%2BH9aT7FF9MXKZ2MsW7C8Cv5ME8%2BH3Qx2RTfr438kjGrK0XE7B7%2BxDB7rkUXI2cQA%3D\"}],\"group\":\"cf-nel\",\"max_age\":604800}"], ["nel", "{\"success_fraction\":0,\"report_to\":\"cf-nel\",\"max_age\":604800}"], ["server", "cloudflare"], ["cf-ray", "7d14a20e9d0a779b-LHR"], ["alt-svc", "h3=\":443\"; ma=86400"]], [["date", "Sat, 03 Jun 2023 02:51:13 GMT"], ["content-type", "image/webp"], ["content-length", "1247622"], ["access-control-allow-origin", "*"], ["cache-control", "public, max-age=31536000"], ["cf-bgj", "imgq:100,h2pri"], ["cf-polished", "origFmt=png, origSize=1909814"], ["content-disposition", "inline; filename=\"womansmile-6.webp\""], ["etag", "\"61bc00c1-1d2436\""], ["last-modified", "Fri, 17 Dec 2021 03:15:13 GMT"], ["vary", "Accept"], ["cf-cache-status", "HIT"], ["age", "284338"], ["accept-ranges", "bytes"], ["report-to", "{\"endpoints\":[{\"url\":\"https:\\/\\/a.nel.cloudflare.com\\/report\\/v3?s=lHAnmDaR8YjBO2oO7cJCZ44evtUrKX3O6EMry8TqOD07B3jOaopUof%2FV9Rdh8aZi1blKUcUgXdO7QMYRK9A2n0yvGrsOA8ahemjFe3PmnR7y%2BbQnMCTEdKlVw9o%3D\"}],\"group\":\"cf-nel\",\"max_age\":604800}"], ["nel", "{\"success_fraction\":0,\"report_to\":\"cf-nel\",\"max_age\":604800}"], ["server", "cloudflare"], ["cf-ray", "7d14a211bec6779b-LHR"], ["alt-svc", "h3=\":443\"; ma=86400"]], [["date", "Sat, 03 Jun 2023 02:51:15 GMT"], ["content-type", "image/svg+xml"], ["vary", "Accept-Encoding"], ["vary", "Accept-Encoding"], ["vary", "Accept-Encoding"], ["vary", "Accept-Encoding"], ["last-modified", "Fri, 17 Dec 2021 03:15:13 GMT"], ["etag", "W/\"61bc00c1-15fe\""], ["cache-control", "public, max-age=31536000"], ["access-control-allow-origin", "*"], ["cf-cache-status", "HIT"], ["age", "2176587"], ["report-to", "{\"endpoints\":[{\"url\":\"https:\\/\\/a.nel.cloudflare.com\\/report\\/v3?s=d0troUulcWxa8l2THIfUrkB2tflV5FVDnOts%2FFyPNPixpG2jhlckug7EMpnwiHMrew1lVJkwf77evJoaPVMzJKApECRna5DV2cUNEadPK6SCvrvgmZwHRLn4Peo%3D\"}],\"group\":\"cf-nel\",\"max_age\":604800}"], ["nel", "{\"success_fraction\":0,\"report_to\":\"cf-nel\",\"max_age\":604800}"], ["server", "cloudflare"], ["cf-ray", "7d14a21b1b29779b-LHR"], ["content-encoding", "br"], ["alt-svc", "h3=\":443\"; ma=86400"]], [["date", "Sat, 03 Jun 2023 02:51:15 GMT"], ["content-type", "image/webp"], ["content-length", "4746"], ["access-control-allow-origin", "*"], ["cache-control", "public, max-age=31536000"], ["cf-bgj", "imgq:100,h2pri"], ["cf-polished", "origFmt=png, origSize=8892"], ["content-disposition", "inline; filename=\"acuity_sm.webp\""], ["etag", "\"61bc00c1-22bc\""], ["last-modified", "Fri, 17 Dec 2021 03:15:13 GMT"], ["vary", "Accept"], ["cf-cache-status", "HIT"], ["age", "1248534"], ["accept-ranges", "bytes"], ["report-to", "{\"endpoints\":[{\"url\":\"https:\\/\\/a.nel.cloudflare.com\\/report\\/v3?s=LEAaCxWJNqzF%2FvInFlJ283dtOELXUMLFD4qCqM3iXGKT0DmxAE%2FuwfBSEpY4Y50hUcFokTRHAlNm4gY60EwG8n7FdB%2FQdjbKVXdAmW7HzjLvodLufFzGFBgwySg%3D\"}],\"group\":\"cf-nel\",\"max_age\":604800}"], ["nel", "{\"success_fraction\":0,\"report_to\":\"cf-nel\",\"max_age\":604800}"], ["server", "cloudflare"], ["cf-ray", "7d14a21b7b51779b-LHR"], ["alt-svc", "h3=\":443\"; ma=86400"]], [["date", "Sat, 03 Jun 2023 02:51:15 GMT"], ["content-type", "image/svg+xml"], ["vary", "Accept-Encoding"], ["vary", "Accept-Encoding"], ["vary", "Accept-Encoding"], ["vary", "Accept-Encoding"], ["last-modified", "Fri, 17 Dec 2021 03:15:13 GMT"], ["etag", "W/\"61bc00c1-f4d\""], ["cache-control", "public, max-age=31536000"], ["access-control-allow-origin", "*"], ["cf-cache-status", "HIT"], ["age", "2162952"], ["report-to", "{\"endpoints\":[{\"url\":\"https:\\/\\/a.nel.cloudflare.com\\/report\\/v3?s=z1hn7RolooCnfcNBFtv8GxhvdHjF6WjFxzmPXR4mYiDecbidYLBDO0MCTrNG9LR4gTO%2BzxEmKcpIt9XAOv3FUSQF6TCHdCM7EOHXFgbBTfReR8aoVwnuZj43U4Q%3D\"}],\"group\":\"cf-nel\",\"max_age\":604800}"], ["nel", "{\"success_fraction\":0,\"report_to\":\"cf-nel\",\"max_age\":604800}"], ["server", "cloudflare"], ["cf-ray", "7d14a21b7b52779b-LHR"], ["content-encoding", "br"], ["alt-svc", "h3=\":443\"; ma=86400"]], [["date", "Sat, 03 Jun 2023 02:51:15 GMT"], ["content-type", "image/svg+xml"], ["vary", "Accept-Encoding"], ["vary", "Accept-Encoding"], ["vary", "Accept-Encoding"], ["vary", "Accept-Encoding"], ["last-modified", "Fri, 17 Dec 2021 03:15:13 GMT"], ["etag", "W/\"61bc00c1-8d6\""], ["cache-control", "public, max-age=31536000"], ["access-control-allow-origin", "*"], ["cf-cache-status", "HIT"], ["age", "9303804"], ["report-to", "{\"endpoints\":[{\"url\":\"https:\\/\\/a.nel.cloudflare.com\\/report\\/v3?s=Tx2HW%2FPEtX5JHLcHiHpiu0R6sE9Hr0nDNkYdizBLtYxKwi5eMxeVF3nfDaYxEbt99JLgGSuxyd6lSxttVScDAmEY%2FWDFBtO1obzXkQPfRdCg60zOK3GxlzDT8KA%3D\"}],\"group\":\"cf-nel\",\"max_age\":604800}"], ["nel", "{\"success_fraction\":0,\"report_to\":\"cf-nel\",\"max_age\":604800}"], ["server", "cloudflare"], ["cf-ray", "7d14a21d1c28779b-LHR"], ["content-encoding", "br"], ["alt-svc", "h3=\":443\"; ma=86400"]], [["date", "Sat, 03 Jun 2023 02:51:16 GMT"], ["content-type", "image/svg+xml"], ["vary", "Accept-Encoding"], ["vary", "Accept-Encoding"], ["vary", "Accept-Encoding"], ["last-modified", "Fri, 17 Dec 2021 03:15:13 GMT"], ["etag", "W/\"61bc00c1-313\""], ["cache-control", "public, max-age=31536000"], ["access-control-allow-origin", "*"], ["cf-cache-status", "HIT"], ["age", "19853821"], ["report-to", "{\"endpoints\":[{\"url\":\"https:\\/\\/a.nel.cloudflare.com\\/report\\/v3?s=2VGx%2FdSCn0X51k9wf8073xXIVWxh5vNC%2FKvEJ1X%2FJBBAvVo0rcwgwlVwGQ4n91kSy0F%2B6DrpJIL%2FDO4uq00hH2ScXOeX5vP8iNSpWNH0ig%2F7Qabja3o6UVhGQZ0%3D\"}],\"group\":\"cf-nel\",\"max_age\":604800}"], ["nel", "{\"success_fraction\":0,\"report_to\":\"cf-nel\",\"max_age\":604800}"], ["server", "cloudflare"], ["cf-ray", "7d14a2240f46779b-LHR"], ["content-encoding", "br"], ["alt-svc", "h3=\":443\"; ma=86400"]], [["date", "Sat, 03 Jun 2023 02:51:16 GMT"], ["content-type", "image/webp"], ["content-length", "2238"], ["access-control-allow-origin", "*"], ["cache-control", "public, max-age=31536000"], ["cf-bgj", "imgq:100,h2pri"], ["cf-polished", "origFmt=png, origSize=5351"], ["content-disposition", "inline; filename=\"alikeaud.webp\""], ["etag", "\"61bc00c1-14e7\""], ["last-modified", "Fri, 17 Dec 2021 03:15:13 GMT"], ["vary", "Accept"], ["cf-cache-status", "HIT"], ["age", "281987"], ["accept-ranges", "bytes"], ["report-to", "{\"endpoints\":[{\"url\":\"https:\\/\\/a.nel.cloudflare.com\\/report\\/v3?s=nWLx7qcfEr4RO6rQZUxk32ywBpijsfFOxYud4LArLFxC2yISQ4FlQohQG8cRfmQlouqeSBnwGdp9WhjBERsBVx5OYwYA3sA%2BtN9mPBeu4sFBxZxoP6d5f0VAgjQ%3D\"}],\"group\":\"cf-nel\",\"max_age\":604800}"], ["nel", "{\"success_fraction\":0,\"report_to\":\"cf-nel\",\"max_age\":604800}"], ["server", "cloudflare"], ["cf-ray", "7d14a2265843779b-LHR"], ["alt-svc", "h3=\":443\"; ma=86400"]], [["date", "Sat, 03 Jun 2023 02:51:16 GMT"], ["content-type", "image/webp"], ["content-length", "14838"], ["access-control-allow-origin", "*"], ["cache-control", "public, max-age=31536000"], ["cf-bgj", "imgq:100,h2pri"], ["cf-polished", "origFmt=png, origSize=34745"], ["content-disposition", "inline; filename=\"amobee-logo-black.webp\""], ["etag", "\"61bc00c1-87b9\""], ["last-modified", "Fri, 17 Dec 2021 03:15:13 GMT"], ["vary", "Accept"], ["cf-cache-status", "HIT"], ["age", "1486988"], ["accept-ranges", "bytes"], ["report-to", "{\"endpoints\":[{\"url\":\"https:\\/\\/a.nel.cloudflare.com\\/report\\/v3?s=lfk%2F6lrerN5%2BhGR9BoKM79rFYgwxKaMmxpnElDEeaqaCKN2S6VJctommKGuC5TOnddtXCbsGzg3P5eXWuq8BcghVBJzV0qfBOa%2BBZCYYAKx4ox5jgOz1L%2FaXOEw%3D\"}],\"group\":\"cf-nel\",\"max_age\":604800}"], ["nel", "{\"success_fraction\":0,\"report_to\":\"cf-nel\",\"max_age\":604800}"], ["server", "cloudflare"], ["cf-ray", "7d14a226a874779b-LHR"], ["alt-svc", "h3=\":443\"; ma=86400"]], [["date", "Sat, 03 Jun 2023 02:51:17 GMT"], ["content-type", "image/webp"], ["content-length", "3540"], ["access-control-allow-origin", "*"], ["cache-control", "public, max-age=31536000"], ["cf-bgj", "imgq:100,h2pri"], ["cf-polished", "origFmt=png, origSize=6506"], ["content-disposition", "inline; filename=\"apollologo.webp\""], ["etag", "\"61bc00c1-196a\""], ["last-modified", "Fri, 17 Dec 2021 03:15:13 GMT"], ["vary", "Accept"], ["cf-cache-status", "HIT"], ["age", "776938"], ["accept-ranges", "bytes"], ["report-to", "{\"endpoints\":[{\"url\":\"https:\\/\\/a.nel.cloudflare.com\\/report\\/v3?s=HQEkAgWdBKvqDNsjRIxJ2ZnE90H2o5WlB8WxJmYNDX0a9uzMAkY5ANy5GeTfpM%2BKinqnAEDQ%2Bozm1%2B%2F3CxFf6YJG%2BuBhzQwSBiLMx93C2Q9ZJRZ9P3u6HMp%2BJsw%3D\"}],\"group\":\"cf-nel\",\"max_age\":604800}"], ["nel", "{\"success_fraction\":0,\"report_to\":\"cf-nel\",\"max_age\":604800}"], ["server", "cloudflare"], ["cf-ray", "7d14a2285929779b-LHR"], ["alt-svc", "h3=\":443\"; ma=86400"]], [["date", "Sat, 03 Jun 2023 02:51:17 GMT"], ["content-type", "image/webp"], ["content-length", "5990"], ["access-control-allow-origin", "*"], ["cache-control", "public, max-age=31536000"], ["cf-bgj", "imgq:100,h2pri"], ["cf-polished", "origFmt=png, origSize=13709"], ["content-disposition", "inline; filename=\"xandrLogo.webp\""], ["etag", "\"63db0266-358d\""], ["last-modified", "Thu, 02 Feb 2023 00:23:02 GMT"], ["vary", "Accept"], ["cf-cache-status", "HIT"], ["age", "1479310"], ["accept-ranges", "bytes"], ["report-to", "{\"endpoints\":[{\"url\":\"https:\\/\\/a.nel.cloudflare.com\\/report\\/v3?s=2ANpaipQvglIJs%2Fx%2F%2FULFLXCoavIY7OvgP0HnUuYkAkMBmmq2AfTZ0uzxPtZdPRWTA3TsaitYVvhQ5hHM7kGUO9OUVX%2BdMF1GmmriCsZuEdYqXloDmju3gmothI%3D\"}],\"group\":\"cf-nel\",\"max_age\":604800}"], ["nel", "{\"success_fraction\":0,\"report_to\":\"cf-nel\",\"max_age\":604800}"], ["server", "cloudflare"], ["cf-ray", "7d14a227b8d4779b-LHR"], ["alt-svc", "h3=\":443\"; ma=86400"]], [["date", "Sat, 03 Jun 2023 02:51:17 GMT"], ["content-type", "image/jpeg"], ["content-length", "19355"], ["access-control-allow-origin", "*"], ["cache-control", "public, max-age=31536000"], ["cf-bgj", "imgq:100,h2pri"], ["cf-polished", "origSize=22467, status=webp_bigger"], ["etag", "\"61bc00c1-57c3\""], ["last-modified", "Fri, 17 Dec 2021 03:15:13 GMT"], ["vary", "Accept-Encoding"], ["cf-cache-status", "HIT"], ["age", "961998"], ["accept-ranges", "bytes"], ["report-to", "{\"endpoints\":[{\"url\":\"https:\\/\\/a.nel.cloudflare.com\\/report\\/v3?s=gukXfSLiS0SVighC05w5Bi6PdTA8czrgo6zOxXiUbeKcfQ9zrkI%2BRzJ%2BkriF8lW3BwKbGi%2F6EVmS0YBbfpqE%2FjlkeORZEqfhsj9XD25hFuqnTuwHlOUndhLSEgs%3D\"}],\"group\":\"cf-nel\",\"max_age\":604800}"], ["nel", "{\"success_fraction\":0,\"report_to\":\"cf-nel\",\"max_age\":604800}"], ["server", "cloudflare"], ["cf-ray", "7d14a228f97f779b-LHR"], ["alt-svc", "h3=\":443\"; ma=86400"]], [["date", "Sat, 03 Jun 2023 02:51:17 GMT"], ["content-type", "image/webp"], ["content-length", "22494"], ["access-control-allow-origin", "*"], ["cache-control", "public, max-age=31536000"], ["cf-bgj", "imgq:100,h2pri"], ["cf-polished", "origFmt=png, origSize=31186"], ["content-disposition", "inline; filename=\"audienceratelogo.webp\""], ["etag", "\"61bc00c1-79d2\""], ["last-modified", "Fri, 17 Dec 2021 03:15:13 GMT"], ["vary", "Accept"], ["cf-cache-status", "HIT"], ["age", "764631"], ["accept-ranges", "bytes"], ["report-to", "{\"endpoints\":[{\"url\":\"https:\\/\\/a.nel.cloudflare.com\\/report\\/v3?s=noe%2FqR6LscOlX6Qssnus00kTXmvSOz%2BV3skdG3UTUL26ncsNpTJXbZQF8XsKqbz2gOb%2Bug9cZP5p7SbRqDIeIYTxuuzAeytzmZgvgl03UYL7pHwdUdVzZ0%2BZMKA%3D\"}],\"group\":\"cf-nel\",\"max_age\":604800}"], ["nel", "{\"success_fraction\":0,\"report_to\":\"cf-nel\",\"max_age\":604800}"], ["server", "cloudflare"], ["cf-ray", "7d14a22c6b2e779b-LHR"], ["alt-svc", "h3=\":443\"; ma=86400"]], [["date", "Sat, 03 Jun 2023 02:51:17 GMT"], ["content-type", "image/webp"], ["content-length", "13908"], ["access-control-allow-origin", "*"], ["cache-control", "public, max-age=31536000"], ["cf-bgj", "imgq:100,h2pri"], ["cf-polished", "origFmt=png, origSize=22957"], ["content-disposition", "inline; filename=\"audigentlogo.webp\""], ["etag", "\"61bc00c1-59ad\""], ["last-modified", "Fri, 17 Dec 2021 03:15:13 GMT"], ["vary", "Accept"], ["cf-cache-status", "HIT"], ["age", "1500092"], ["accept-ranges", "bytes"], ["report-to", "{\"endpoints\":[{\"url\":\"https:\\/\\/a.nel.cloudflare.com\\/report\\/v3?s=2qtbDHrk0pRsIZJ9O2V6GFQbeULDQ0IJPpGiCb345kTH%2BUcqKun46qrn1PtaTD0UvfPR4vTVAQAOwlpxwiqCstPhovMpd%2B44x8vTWHKVhb%2B%2B7cbCUk%2BPuqGbc1c%3D\"}],\"group\":\"cf-nel\",\"max_age\":604800}"], ["nel", "{\"success_fraction\":0,\"report_to\":\"cf-nel\",\"max_age\":604800}"], ["server", "cloudflare"], ["cf-ray", "7d14a22d0b80779b-LHR"], ["alt-svc", "h3=\":443\"; ma=86400"]], [["date", "Sat, 03 Jun 2023 02:51:18 GMT"], ["content-type", "image/webp"], ["content-length", "2718"], ["access-control-allow-origin", "*"], ["cache-control", "public, max-age=31536000"], ["cf-bgj", "imgq:100,h2pri"], ["cf-polished", "origFmt=png, origSize=6040"], ["content-disposition", "inline; filename=\"beeswaxlogo.webp\""], ["etag", "\"61bc00c1-1798\""], ["last-modified", "Fri, 17 Dec 2021 03:15:13 GMT"], ["vary", "Accept"], ["cf-cache-status", "HIT"], ["age", "1488831"], ["accept-ranges", "bytes"], ["report-to", "{\"endpoints\":[{\"url\":\"https:\\/\\/a.nel.cloudflare.com\\/report\\/v3?s=63zzpvicpGBeDHlQ6%2BPGNnoucht19wD3p7UVikhegcA12fab%2FCm9poo87ZDqtl8OiDR2SUXyTT2dmj4G5Cg922iUlNZQp1RAj90fGOq6k8X7IJFolhihVCcGZrc%3D\"}],\"group\":\"cf-nel\",\"max_age\":604800}"], ["nel", "{\"success_fraction\":0,\"report_to\":\"cf-nel\",\"max_age\":604800}"], ["server", "cloudflare"], ["cf-ray", "7d14a22d7baa779b-LHR"], ["alt-svc", "h3=\":443\"; ma=86400"]], [["date", "Sat, 03 Jun 2023 02:51:18 GMT"], ["content-type", "image/webp"], ["content-length", "2922"], ["access-control-allow-origin", "*"], ["cache-control", "public, max-age=31536000"], ["cf-bgj", "imgq:100,h2pri"], ["cf-polished", "origFmt=png, origSize=8072"], ["content-disposition", "inline; filename=\"branchlogo.webp\""], ["etag", "\"61bc00c1-1f88\""], ["last-modified", "Fri, 17 Dec 2021 03:15:13 GMT"], ["vary", "Accept"], ["cf-cache-status", "HIT"], ["age", "1486990"], ["accept-ranges", "bytes"], ["report-to", "{\"endpoints\":[{\"url\":\"https:\\/\\/a.nel.cloudflare.com\\/report\\/v3?s=%2BYrLiB2BVwYEA8axj3%2FSAuJGslo0zvy8pxWRQwqNOOmNQPNNAKvPh6knxMDlK%2BAiciSDybeh5fugugJV7T1MoDTo0IKS%2FKbiw8vlWk5hkcA7q1RtiizcyZIlDFg%3D\"}],\"group\":\"cf-nel\",\"max_age\":604800}"], ["nel", "{\"success_fraction\":0,\"report_to\":\"cf-nel\",\"max_age\":604800}"], ["server", "cloudflare"], ["cf-ray", "7d14a22e9c33779b-LHR"], ["alt-svc", "h3=\":443\"; ma=86400"]], [["date", "Sat, 03 Jun 2023 02:51:18 GMT"], ["content-type", "image/webp"], ["content-length", "11416"], ["access-control-allow-origin", "*"], ["cache-control", "public, max-age=31536000"], ["cf-bgj", "imgq:100,h2pri"], ["cf-polished", "origFmt=png, origSize=99034"], ["content-disposition", "inline; filename=\"digital_blue_notag.webp\""], ["etag", "\"61bc00c1-182da\""], ["last-modified", "Fri, 17 Dec 2021 03:15:13 GMT"], ["vary", "Accept"], ["cf-cache-status", "HIT"], ["age", "758343"], ["accept-ranges", "bytes"], ["report-to", "{\"endpoints\":[{\"url\":\"https:\\/\\/a.nel.cloudflare.com\\/report\\/v3?s=dqSnAf%2Bzu0QHcRzjnHsA37v2Gg%2FsRulRauZUAIztniTJmq2FCrzmVtPjQHgcITLr0%2B8%2FJ5IU15%2FwmZd2XZQIDOrgV6V6O0DlbbmX6OJMVkjZwH3QUr8LQYAaRlU%3D\"}],\"group\":\"cf-nel\",\"max_age\":604800}"], ["nel", "{\"success_fraction\":0,\"report_to\":\"cf-nel\",\"max_age\":604800}"], ["server", "cloudflare"], ["cf-ray", "7d14a22f8ca9779b-LHR"], ["alt-svc", "h3=\":443\"; ma=86400"]], [["date", "Sat, 03 Jun 2023 02:51:18 GMT"], ["content-type", "image/svg+xml"], ["vary", "Accept-Encoding"], ["vary", "Accept-Encoding"], ["vary", "Accept-Encoding"], ["vary", "Accept-Encoding"], ["last-modified", "Fri, 17 Dec 2021 03:15:13 GMT"], ["etag", "W/\"61bc00c1-f80\""], ["cache-control", "public, max-age=31536000"], ["access-control-allow-origin", "*"], ["cf-cache-status", "HIT"], ["age", "9415697"], ["report-to", "{\"endpoints\":[{\"url\":\"https:\\/\\/a.nel.cloudflare.com\\/report\\/v3?s=jVGUj%2FWCb4fxQ%2FUsOEdVYr3fnIDcfzUqnkOS%2FvxOIsBSFA2rRBV9qPh0wCaJVvk69pskXamzhAPmTdAaBPmniUhwt3gV77dcmZFs94U1XYP67FouG9eb7izpVks%3D\"}],\"group\":\"cf-nel\",\"max_age\":604800}"], ["nel", "{\"success_fraction\":0,\"report_to\":\"cf-nel\",\"max_age\":604800}"], ["server", "cloudflare"], ["cf-ray", "7d14a22ffce3779b-LHR"], ["content-encoding", "br"], ["alt-svc", "h3=\":443\"; ma=86400"]], [["date", "Sat, 03 Jun 2023 02:51:18 GMT"], ["content-type", "image/webp"], ["content-length", "15530"], ["access-control-allow-origin", "*"], ["cache-control", "public, max-age=31536000"], ["cf-bgj", "imgq:100,h2pri"], ["cf-polished", "origFmt=png, origSize=31413"], ["content-disposition", "inline; filename=\"clickagylogo.webp\""], ["etag", "\"61bc00c1-7ab5\""], ["last-modified", "Fri, 17 Dec 2021 03:15:13 GMT"], ["vary", "Accept"], ["cf-cache-status", "HIT"], ["age", "2162954"], ["accept-ranges", "bytes"], ["report-to", "{\"endpoints\":[{\"url\":\"https:\\/\\/a.nel.cloudflare.com\\/report\\/v3?s=JB%2FThHZsMIw9cSpD5TPqvS%2B0LFG5PZaqijj8YWDTjwNGpw46cWjy0RjMdr7OaG%2F24po5EtARKRqZBR%2FGBr2rjLRMperksxoeLJdjnY%2Fj1TrVEok2iG7RmjnDRHA%3D\"}],\"group\":\"cf-nel\",\"max_age\":604800}"], ["nel", "{\"success_fraction\":0,\"report_to\":\"cf-nel\",\"max_age\":604800}"], ["server", "cloudflare"], ["cf-ray", "7d14a2306d0d779b-LHR"], ["alt-svc", "h3=\":443\"; ma=86400"]], [["date", "Sat, 03 Jun 2023 02:51:18 GMT"], ["content-type", "image/svg+xml"], ["vary", "Accept-Encoding"], ["vary", "Accept-Encoding"], ["vary", "Accept-Encoding"], ["last-modified", "Fri, 17 Dec 2021 03:15:13 GMT"], ["etag", "W/\"61bc00c1-17dd\""], ["cache-control", "public, max-age=31536000"], ["access-control-allow-origin", "*"], ["cf-cache-status", "HIT"], ["age", "19853823"], ["report-to", "{\"endpoints\":[{\"url\":\"https:\\/\\/a.nel.cloudflare.com\\/report\\/v3?s=Sp1J0Omh80D0P818GAd5R7hdHJsV5bmmfoGsB7DFxTjexIx6D3o8ZcquCgFRIYL1FzilAJmXtb2%2F2cJNIOuJC0RFoz6CoYNGEm4eJK3qh3Iuq%2F4QIaOcCZ5zJCQ%3D\"}],\"group\":\"cf-nel\",\"max_age\":604800}"], ["nel", "{\"success_fraction\":0,\"report_to\":\"cf-nel\",\"max_age\":604800}"], ["server", "cloudflare"], ["cf-ray", "7d14a2314d81779b-LHR"], ["content-encoding", "br"], ["alt-svc", "h3=\":443\"; ma=86400"]], [["date", "Sat, 03 Jun 2023 02:51:18 GMT"], ["content-type", "image/webp"], ["content-length", "5370"], ["access-control-allow-origin", "*"], ["cache-control", "public, max-age=31536000"], ["cf-bgj", "imgq:100,h2pri"], ["cf-polished", "origFmt=png, origSize=8410"], ["content-disposition", "inline; filename=\"CrossPixel-logo-notagline-300x68-1.webp\""], ["etag", "\"61bc00c1-20da\""], ["last-modified", "Fri, 17 Dec 2021 03:15:13 GMT"], ["vary", "Accept"], ["cf-cache-status", "HIT"], ["age", "3751433"], ["accept-ranges", "bytes"], ["report-to", "{\"endpoints\":[{\"url\":\"https:\\/\\/a.nel.cloudflare.com\\/report\\/v3?s=odlE7VhyMZ28LW55szjmh6wOICnLs5F2ID14FOJ5gd1Uh%2BvAp8dPB6XtEZ5bEQI5V6lnHJ9frDYAoXyRZtQ0W02rBESn%2FuoqQ%2FORpWD3bR7MCZlTPkklYRJWijk%3D\"}],\"group\":\"cf-nel\",\"max_age\":604800}"], ["nel", "{\"success_fraction\":0,\"report_to\":\"cf-nel\",\"max_age\":604800}"], ["server", "cloudflare"], ["cf-ray", "7d14a232ce1a779b-LHR"], ["alt-svc", "h3=\":443\"; ma=86400"]], [["date", "Sat, 03 Jun 2023 02:51:18 GMT"], ["content-type", "image/webp"], ["content-length", "8602"], ["access-control-allow-origin", "*"], ["cache-control", "public, max-age=31536000"], ["cf-bgj", "imgq:100,h2pri"], ["cf-polished", "origFmt=png, origSize=30924"], ["content-disposition", "inline; filename=\"cuebiqlogo.webp\""], ["etag", "\"61bc00c1-78cc\""], ["last-modified", "Fri, 17 Dec 2021 03:15:13 GMT"], ["vary", "Accept"], ["cf-cache-status", "HIT"], ["age", "1488827"], ["accept-ranges", "bytes"], ["report-to", "{\"endpoints\":[{\"url\":\"https:\\/\\/a.nel.cloudflare.com\\/report\\/v3?s=klnQKxVulBvezDj8moAthj86kVWa7g30aj4B3gq1UDN6sU10bwOQRJxphs5kGlGdud2zzgimikzBLZg88mLiJaGFiSD0ET%2BPGbGR9SiVq6PK1KK6xCj34qz92oQ%3D\"}],\"group\":\"cf-nel\",\"max_age\":604800}"], ["nel", "{\"success_fraction\":0,\"report_to\":\"cf-nel\",\"max_age\":604800}"], ["server", "cloudflare"], ["cf-ray", "7d14a2338e7f779b-LHR"], ["alt-svc", "h3=\":443\"; ma=86400"]], [["date", "Sat, 03 Jun 2023 02:51:19 GMT"], ["content-type", "image/webp"], ["content-length", "3406"], ["access-control-allow-origin", "*"], ["cache-control", "public, max-age=31536000"], ["cf-bgj", "imgq:100,h2pri"], ["cf-polished", "origFmt=png, origSize=4597"], ["content-disposition", "inline; filename=\"datonics.webp\""], ["etag", "\"61bc00c1-11f5\""], ["last-modified", "Fri, 17 Dec 2021 03:15:13 GMT"], ["vary", "Accept"], ["cf-cache-status", "HIT"], ["age", "281987"], ["accept-ranges", "bytes"], ["report-to", "{\"endpoints\":[{\"url\":\"https:\\/\\/a.nel.cloudflare.com\\/report\\/v3?s=6zltnOuxQ5TsZmu42A%2FCC1qDA1lEXEPFww2LI0C6h10dkvqe4iLuUY6bbbBBGlFRhlb%2Bb778Aedd4TV5vq7waIh6ZBl3z5s8atjrpPAxG7E%2FaTKVTbTYkmpq9pc%3D\"}],\"group\":\"cf-nel\",\"max_age\":604800}"], ["nel", "{\"success_fraction\":0,\"report_to\":\"cf-nel\",\"max_age\":604800}"], ["server", "cloudflare"], ["cf-ray", "7d14a238c936779b-LHR"], ["alt-svc", "h3=\":443\"; ma=86400"]], [["date", "Sat, 03 Jun 2023 02:51:19 GMT"], ["content-type", "image/webp"], ["content-length", "8606"], ["access-control-allow-origin", "*"], ["cache-control", "public, max-age=31536000"], ["cf-bgj", "imgq:100,h2pri"], ["cf-polished", "origFmt=png, origSize=30732"], ["content-disposition", "inline; filename=\"foursquareLogo.webp\""], ["etag", "\"62bc91ef-780c\""], ["last-modified", "Wed, 29 Jun 2022 17:54:55 GMT"], ["vary", "Accept"], ["cf-cache-status", "HIT"], ["age", "3207540"], ["accept-ranges", "bytes"], ["report-to", "{\"endpoints\":[{\"url\":\"https:\\/\\/a.nel.cloudflare.com\\/report\\/v3?s=DC1GPZXGj%2Br4Hi5AB0TgmgR7ToTu3lTnUh0GFSO0JfHZP%2BqSMc46RKqGqmFNDECY8lIgQhViMvHhZSUfb6A%2FSPJFqujb5SIVkNXsuTu7CjoY7x9jph6k7jNha4U%3D\"}],\"group\":\"cf-nel\",\"max_age\":604800}"], ["nel", "{\"success_fraction\":0,\"report_to\":\"cf-nel\",\"max_age\":604800}"], ["server", "cloudflare"], ["cf-ray", "7d14a238c934779b-LHR"], ["alt-svc", "h3=\":443\"; ma=86400"]], [["date", "Sat, 03 Jun 2023 02:51:19 GMT"], ["content-type", "image/webp"], ["content-length", "6730"], ["access-control-allow-origin", "*"], ["cache-control", "public, max-age=31536000"], ["cf-bgj", "imgq:100,h2pri"], ["cf-polished", "origFmt=png, origSize=11401"], ["content-disposition", "inline; filename=\"eyeotalogo.webp\""], ["etag", "\"61bc00c1-2c89\""], ["last-modified", "Fri, 17 Dec 2021 03:15:13 GMT"], ["vary", "Accept"], ["cf-cache-status", "HIT"], ["age", "2162955"], ["accept-ranges", "bytes"], ["report-to", "{\"endpoints\":[{\"url\":\"https:\\/\\/a.nel.cloudflare.com\\/report\\/v3?s=SP30OcV%2BsflEK1QnFRt2KJJDec7tn%2FGKO4Xfx2Zou3ZNQDKFoz0EPGuz5bWBjDwFsXql%2BoBp832JKEfPEYI6ih4kRJ6tm9olOfs9nC%2Bby88p5DuKm6X27odTKXs%3D\"}],\"group\":\"cf-nel\",\"max_age\":604800}"], ["nel", "{\"success_fraction\":0,\"report_to\":\"cf-nel\",\"max_age\":604800}"], ["server", "cloudflare"], ["cf-ray", "7d14a238c935779b-LHR"], ["alt-svc", "h3=\":443\"; ma=86400"]], [["date", "Sat, 03 Jun 2023 02:51:19 GMT"], ["content-type", "image/webp"], ["content-length", "9314"], ["access-control-allow-origin", "*"], ["cache-control", "public, max-age=31536000"], ["cf-bgj", "imgq:100,h2pri"], ["cf-polished", "origFmt=png, origSize=16453"], ["content-disposition", "inline; filename=\"NAI_rings-1-1.webp\""], ["etag", "\"61bc00c1-4045\""], ["last-modified", "Fri, 17 Dec 2021 03:15:13 GMT"], ["vary", "Accept"], ["cf-cache-status", "HIT"], ["age", "500345"], ["accept-ranges", "bytes"], ["report-to", "{\"endpoints\":[{\"url\":\"https:\\/\\/a.nel.cloudflare.com\\/report\\/v3?s=AS4fg2cPtUFiJsndjiNG3pgXzccxjnKmewATLsF9P12AZjBVDsSxLNTohrLBzVaqI2akPWCOKP20gmUyEuUed1b0%2F9rlYkNKdaE1nisuhCkx4BwWjg8mITyJdJY%3D\"}],\"group\":\"cf-nel\",\"max_age\":604800}"], ["nel", "{\"success_fraction\":0,\"report_to\":\"cf-nel\",\"max_age\":604800}"], ["server", "cloudflare"], ["cf-ray", "7d14a239295c779b-LHR"], ["alt-svc", "h3=\":443\"; ma=86400"]], [["date", "Sat, 03 Jun 2023 02:51:21 GMT"], ["content-type", "image/png"], ["content-length", "20918"], ["access-control-allow-origin", "*"], ["cache-control", "public, max-age=31536000"], ["cf-bgj", "imgq:100,h2pri"], ["cf-polished", "origSize=59844, status=webp_bigger"], ["etag", "\"61bc00c1-e9c4\""], ["last-modified", "Fri, 17 Dec 2021 03:15:13 GMT"], ["vary", "Accept-Encoding"], ["cf-cache-status", "HIT"], ["age", "971639"], ["accept-ranges", "bytes"], ["report-to", "{\"endpoints\":[{\"url\":\"https:\\/\\/a.nel.cloudflare.com\\/report\\/v3?s=soXJ2FKsobSH5mwQD4H3I3jTqOlTIDS%2FYYxZ1twz4B%2Bp4Vz355A7w%2B6dJ1%2F9xWxPpv%2BBm7QH0TsKPNEvfUXw%2BV6ilL1i64XKVVJ8gr36yDHRRidg0f31MuzTqpA%3D\"}],\"group\":\"cf-nel\",\"max_age\":604800}"], ["nel", "{\"success_fraction\":0,\"report_to\":\"cf-nel\",\"max_age\":604800}"], ["server", "cloudflare"], ["cf-ray", "7d14a241ed5a779b-LHR"], ["alt-svc", "h3=\":443\"; ma=86400"]], [["strict-transport-security", "max-age=10886400; includeSubDomains; preload"], ["x-content-type-options", "nosniff"], ["content-encoding", "gzip"], ["cross-origin-resource-policy", "cross-origin"], ["server", "Golfe2"], ["content-length", "20737"], ["date", "Sat, 03 Jun 2023 01:04:51 GMT"], ["expires", "Sat, 03 Jun 2023 03:04:51 GMT"], ["cache-control", "public, max-age=7200"], ["age", "6392"], ["last-modified", "Mon, 17 Apr 2023 22:36:01 GMT"], ["content-type", "text/javascript"], ["vary", "Accept-Encoding"], ["alt-svc", "h3=\":443\"; ma=2592000,h3-29=\":443\"; ma=2592000"]], [["access-control-allow-origin", "https://thenai.org"], ["date", "Sat, 03 Jun 2023 02:51:24 GMT"], ["pragma", "no-cache"], ["expires", "Fri, 01 Jan 1990 00:00:00 GMT"], ["cache-control", "no-cache, no-store, must-revalidate"], ["last-modified", "Sun, 17 May 1998 03:00:00 GMT"], ["access-control-allow-credentials", "true"], ["x-content-type-options", "nosniff"], ["content-type", "text/plain"], ["cross-origin-resource-policy", "cross-origin"], ["server", "Golfe2"], ["content-length", "1"], ["alt-svc", "h3=\":443\"; ma=2592000,h3-29=\":443\"; ma=2592000"]]], "request_date": [1685760654685.099, 1685760656257.221, 1685760657505.833, 1685760657586.625, 1685760657668.228, 1685760657735.791, 1685760657739.967, 1685760657834.51, 1685760658408.252, 1685760658416.584, 1685760659111.037, 1685760659942.418, 1685760660817.095, 1685760661073.526, 1685760661075.178, 1685760661201.564, 1685760661280.968, 1685760661881.96, 1685760661921.968, 1685760662244.563, 1685760662275.953, 1685760662540.045, 1685760662711.238, 1685760663211.305, 1685760663617.267, 1685760664092.289, 1685760664239.12, 1685760665126.893, 1685760665456.757, 1685760665785.308, 1685760666729.539, 1685760673035.7, 1685760673500.968, 1685760674995.476, 1685760675014.235, 1685760675051.25, 1685760675261.33, 1685760676388.614, 1685760676735.804, 1685760676861.731, 1685760676979.187, 1685760677027.087, 1685760677064.338, 1685760677799.035, 1685760677804.918, 1685760677951.794, 1685760678151.418, 1685760678307.086, 1685760678310.535, 1685760678407.153, 1685760678576.398, 1685760678766.12, 1685760678952.756, 1685760679546.07, 1685760679735.561, 1685760679739.183, 1685760679822.646, 1685760679824.285, 1685760683844.88, 1685760684551.666], "x_domain_redirects": [], "cookies": [{"domain": ".thenai.org", "expiry": 1685760744, "httpOnly": false, "name": "_gat_gtag_UA_2473248_1", "path": "/", "sameSite": "Lax", "secure": false, "value": "1"}, {"domain": ".thenai.org", "expiry": 1685847084, "httpOnly": false, "name": "_gid", "path": "/", "sameSite": "Lax", "secure": false, "value": "GA1.2.100496418.1685760684"}, {"domain": ".thenai.org", "expiry": 1720320684, "httpOnly": false, "name": "_ga", "path": "/", "sameSite": "Lax", "secure": false, "value": "GA1.2.50140279.1685760684"}], "third_party_request_domains": ["typekit.net", "thenai.org"], "third_party_response_domains": ["thenai.org", "w.org"]}